{
  "tztotrazwebinfo": [
    {
      "TCODICLIE": "0266",
      "TNOMBCLIE": "LACOSTE",
      "TCODIESTICLIE": "DH2930-23",
      "TNUMEVERSCLIE": "02",
      "TCODIETIQCLIEXEDI": "031",
      "TCODIETIQCLIE": "NOIR",
      "TDESCETIQCLIE": "NOIR",
      "TCODITALL": "8",
      "TCODIESTINETT": "A2523",
      "TNUMEVERSESTINETT": "01",
      "TDESCPREN": "Ss collar & placket",
      "TTIPOPREN": "Q1",
      "TDESCTIPOPREN": "Collar & Placket",
      "TCODIPROG": "000562",
      "TDESCPROG": "Otra Composición",
      "TGRUPMEDI": "RG",
      "TDESCGRUPMEDI": "Regular",
      "TINDIEDAD": "A",
      "TDESCEDAD": "Adulto",
      "TINDIGENE": "H",
      "TDESCGENE": "Hombres",
      "TGENDER": "Hombre",
      "TCLASIFIC": "C",
      "TDESCCLASPREN": "Prenda de Segunda calidad",
      "TDESCUBIC": "En carga (APT)",
      "TDIREBUSI": "N"
    }
  ],
  "tztotrazwebalma": [
    {
      "TNUMECAJA": "17546308",
      "TCANTPREN": 1,
      "TPURCORDE": "7283541",
      "TCODITEMP": "2026ET",
      "TNUMEORDEFABR": "E26UJL25R",
      "TCODIDEST": "BRA",
      "TDESCDEST": "Brasil",
      "TNUMEEMBA": "D3518",
      "TDESCTIPOCAJA": "Caja de prendas de segunda",
      "TFECHRECEALMA": "2026-02-07 05:17:26",
      "TCODIPERSRECEALMA": "O00A859",
      "TNOMBPERSRECEALMA": "Luis Sanchez"
    }
  ],
  "tztotrazwebacab": [
    {
      "TNUMECAJA": "17546308",
      "TFECHPESA": "2026-02-07 05:13:05",
      "TCODIPERSPESA": "O00F311",
      "TNOMBPERSPESA": "Juan Martinez",
      "TPESOBRUT": 13.1,
      "TPESONETO": 11.77,
      "TFECHEMPA": "2026-02-06 12:10:37",
      "TCODIPERSEMPA": "O00B958",
      "TNOMBPERSEMPA": "Dina Muñoz",
      "TPRENINSPMEDI": "0",
      "TFECHRECEBANDCOST": "2026-01-30 12:49:50",
      "TCODIRECEBANDCOST": "O00F311",
      "TNOMBRECEBANDCOST": "Juan Martinez",
      "TTIPOTICK": "O",
      "TDESCTIPOTICK": "Prenda regular"
    }
  ],
  "tztotrazwebcost": [
    {
      "TORDECOST": "925257",
      "TNUMEPEDI": "695400",
      "TNUMECORR": "374",
      "TNUMEPAQU": "09",
      "TFECHCLAS": "2026-01-29 20:19:02",
      "TCODIPERSCLAS": "O00B874",
      "TNOMBPERSCLAS": "Karim Sutacuro",
      "TCODIBAND": "J9086",
      "TNUMELINECOST": "18",
      "TDESCPLANCOST": "Vulcano",
      "TCODIPERSSUPE": "E001297",
      "TNOMBPERSSUPE": "Myriam Joya",
      "TFECHDESPCORT": "2025-12-23 12:41:45"
    }
  ],
  "tztotrazwebcostoper": [
    {
      "TCODIPERS": "O00K400",
      "TNOMBPERS": "Santos Litano",
      "TNUMEOPERESPE": 8770,
      "TCODIOPERESPEVARISECU": "00999000000877000007",
      "TDESCOPERESPE": "Orillar Basta Manga",
      "TFECHLECT": "2026-01-24 00:00:00",
      "TCODITICK": "000891453543"
    },
    {
      "TCODIPERS": "O00K368",
      "TNOMBPERS": "Maria Coquinche",
      "TNUMEOPERESPE": 42077,
      "TCODIOPERESPEVARISECU": "00282000004207700001",
      "TDESCOPERESPE": "Unir Hombros Con Cinta",
      "TFECHLECT": "2026-01-15 00:00:00",
      "TCODITICK": "002702877946"
    },
    {
      "TCODIPERS": "O00K545",
      "TNOMBPERS": "Lizeth Murillo",
      "TNUMEOPERESPE": 8170,
      "TCODIOPERESPEVARISECU": "00999000000817000003",
      "TDESCOPERESPE": "Recortar Banda Cuello..",
      "TFECHLECT": "2026-01-19 00:00:00",
      "TCODITICK": "000613525052"
    },
    {
      "TCODIPERS": "O00K571",
      "TNOMBPERS": "Janet Ramirez",
      "TNUMEOPERESPE": 41632,
      "TCODIOPERESPEVARISECU": "00282000004163200003",
      "TDESCOPERESPE": "Peg Cue Box Sin Embolsado",
      "TFECHLECT": "2026-01-15 00:00:00",
      "TCODITICK": "002162470141"
    },
    {
      "TCODIPERS": "O001192",
      "TNOMBPERS": "Sandra Quedas",
      "TNUMEOPERESPE": 41258,
      "TCODIOPERESPEVARISECU": "00282000004125800004",
      "TDESCOPERESPE": "Asentar Cuello",
      "TFECHLECT": "2026-01-16 00:00:00",
      "TCODITICK": "003953366012"
    },
    {
      "TCODIPERS": "O002752",
      "TNOMBPERS": "Martha Aguilar",
      "TNUMEOPERESPE": 4782,
      "TCODIOPERESPEVARISECU": "00999000000478201008",
      "TDESCOPERESPE": "Prep Y/O Peg Collareta/Cinta De Vents",
      "TFECHLECT": "2026-01-29 00:00:00",
      "TCODITICK": "000215610386"
    },
    {
      "TCODIPERS": "O00K543",
      "TNOMBPERS": "Jackelin Quito",
      "TNUMEOPERESPE": 6581,
      "TCODIOPERESPEVARISECU": "00142000000658100001",
      "TDESCOPERESPE": "Pegar Etiquetas",
      "TFECHLECT": "2026-01-09 00:00:00",
      "TCODITICK": "006224783601"
    },
    {
      "TCODIPERS": "O00K368",
      "TNOMBPERS": "Maria Coquinche",
      "TNUMEOPERESPE": 42078,
      "TCODIOPERESPEVARISECU": "00282000004207800002",
      "TDESCOPERESPE": "Pespuntar Hombros",
      "TFECHLECT": "2026-01-15 00:00:00",
      "TCODITICK": "007217852250"
    },
    {
      "TCODIPERS": "O00K400",
      "TNOMBPERS": "Santos Litano",
      "TNUMEOPERESPE": 41695,
      "TCODIOPERESPEVARISECU": "00282000004169500007",
      "TDESCOPERESPE": "Peg.Mga Y/O Cerr Cos",
      "TFECHLECT": "2026-01-26 00:00:00",
      "TCODITICK": "004312087784"
    },
    {
      "TCODIPERS": "O00D379",
      "TNOMBPERS": "Ever Raico",
      "TNUMEOPERESPE": 10753,
      "TCODIOPERESPEVARISECU": "00282000001075300009",
      "TDESCOPERESPE": "Basta Faldon",
      "TFECHLECT": "2026-01-16 00:00:00",
      "TCODITICK": "005112376860"
    },
    {
      "TCODIPERS": "O00K545",
      "TNOMBPERS": "Lizeth Murillo",
      "TNUMEOPERESPE": 2144,
      "TCODIOPERESPEVARISECU": "00999000000214400001",
      "TDESCOPERESPE": "Recorte Faldon",
      "TFECHLECT": "2026-01-15 00:00:00",
      "TCODITICK": "002807484845"
    },
    {
      "TCODIPERS": "O002752",
      "TNOMBPERS": "Martha Aguilar",
      "TNUMEOPERESPE": 41636,
      "TCODIOPERESPEVARISECU": "00282000004163600014",
      "TDESCOPERESPE": "Pegar/Twill Abertura (Vents/Yugo)",
      "TFECHLECT": "2026-01-29 00:00:00",
      "TCODITICK": "008035372075"
    },
    {
      "TCODIPERS": "O00K545",
      "TNOMBPERS": "Lizeth Murillo",
      "TNUMEOPERESPE": 2084,
      "TCODIOPERESPEVARISECU": "00282000000208400015",
      "TDESCOPERESPE": "Atracar Abertura",
      "TFECHLECT": "2026-01-30 00:00:00",
      "TCODITICK": "003937569037"
    },
    {
      "TCODIPERS": "O001951",
      "TNOMBPERS": "Miryam Macedo",
      "TNUMEOPERESPE": 21547,
      "TCODIOPERESPEVARISECU": "00282000002154700010",
      "TDESCOPERESPE": "Ojalar",
      "TFECHLECT": "2026-01-26 00:00:00",
      "TCODITICK": "007798495060"
    },
    {
      "TCODIPERS": "O00D919",
      "TNOMBPERS": "Josue Reyes",
      "TNUMEOPERESPE": 21548,
      "TCODIOPERESPEVARISECU": "00282000002154800011",
      "TDESCOPERESPE": "Botonar",
      "TFECHLECT": "2026-01-26 00:00:00",
      "TCODITICK": "007474894827"
    },
    {
      "TCODIPERS": "O002975",
      "TNOMBPERS": "Maria Jurado",
      "TNUMEOPERESPE": 41995,
      "TCODIOPERESPEVARISECU": "00282000004199502016",
      "TDESCOPERESPE": "Pegar Pechera",
      "TFECHLECT": "2026-01-16 00:00:00",
      "TCODITICK": "003196545100"
    },
    {
      "TCODIPERS": "O007305",
      "TNOMBPERS": "Maria Puelles",
      "TNUMEOPERESPE": 42926,
      "TCODIOPERESPEVARISECU": "00999000004292600004",
      "TDESCOPERESPE": "Pesp/Asent Pechera",
      "TFECHLECT": "2026-01-23 00:00:00",
      "TCODITICK": "006629483668"
    },
    {
      "TCODIPERS": "O00K545",
      "TNOMBPERS": "Lizeth Murillo",
      "TNUMEOPERESPE": 9466,
      "TCODIOPERESPEVARISECU": "00219000000946600002",
      "TDESCOPERESPE": "Pespuntar Mangas",
      "TFECHLECT": "2026-01-13 00:00:00",
      "TCODITICK": "005276355249"
    },
    {
      "TCODIPERS": "O00D944",
      "TNOMBPERS": "Marco Romero",
      "TNUMEOPERESPE": 42434,
      "TCODIOPERESPEVARISECU": "00999000004243400005",
      "TDESCOPERESPE": "Fijar Pechera Set-On  (----)",
      "TFECHLECT": "2026-01-24 00:00:00",
      "TCODITICK": "000391619341"
    },
    {
      "TCODIPERS": "O00D334",
      "TNOMBPERS": "Magda Martinez",
      "TNUMEOPERESPE": 34841,
      "TCODIOPERESPEVARISECU": "00219000003484100001",
      "TDESCOPERESPE": "Pegar Puño/Rect+Cerr Manga Corta",
      "TFECHLECT": "2026-01-13 00:00:00",
      "TCODITICK": "001851649884"
    }
  ],
  "tztotrazwebcort": [
    {
      "TNUMEORDECORT": "313475",
      "TNUMETEND": "00896911",
      "TFECHDESPCORT": "2025-12-23 12:41:45"
    }
  ],
  "tztotrazwebcortoper": [
    {
      "TCODIOPER": "01",
      "TDESCOPER": "Tendido",
      "TFECHLECT": "2025-12-21 06:34:27",
      "TCODIPERS": "O00B578",
      "TNOMBPERS": "Eder Leiva",
      "TNUMETICK": "013411"
    },
    {
      "TCODIOPER": "01",
      "TDESCOPER": "Tendido",
      "TFECHLECT": "2025-12-21 06:34:27",
      "TCODIPERS": "O00D506",
      "TNOMBPERS": "Omar Loayza",
      "TNUMETICK": "013412"
    },
    {
      "TCODIOPER": "03",
      "TDESCOPER": "Corte",
      "TFECHLECT": "2025-12-22 09:32:01",
      "TCODIPERS": "O002183",
      "TNOMBPERS": "Javier Erazo",
      "TNUMETICK": "013413"
    },
    {
      "TCODIOPER": "03",
      "TDESCOPER": "Corte",
      "TFECHLECT": "2025-12-22 09:32:01",
      "TCODIPERS": "O002183",
      "TNOMBPERS": "Javier Erazo",
      "TNUMETICK": "013415"
    },
    {
      "TCODIOPER": "04",
      "TDESCOPER": "Numeracion",
      "TFECHLECT": "2025-12-22 12:13:44",
      "TCODIPERS": "O008208",
      "TNOMBPERS": "Eriberto Ipanaque",
      "TNUMETICK": "013452"
    },
    {
      "TCODIOPER": "04",
      "TDESCOPER": "Numeracion",
      "TFECHLECT": "2025-12-22 12:13:44",
      "TCODIPERS": "O008208",
      "TNOMBPERS": "Eriberto Ipanaque",
      "TNUMETICK": "013453"
    }
  ],
  "tztotrazwebtint": [
    {
      "TNUMEOB": 4366899,
      "TTELAPRIN": "0",
      "TTIPOARTI": "CUELLO",
      "TNUMEUD": 913666,
      "TKILOPROG": 11.932391101542104,
      "TREDUACAB": 1186706,
      "TCODITELA": "2741K",
      "TDESCTELA": "Cu-ce-g12-c3-c241p0-lm90-16 1/8 - 3 3/4",
      "TTIPOCOLN": "C",
      "TDESCTIPOCOLN": "Color entero",
      "TNUMECOLN": "73232",
      "TDESCCOLN": "Noir 031 fw24",
      "TTIPOTELA": "E",
      "TDESCTIPOTELA": "Color Entero",
      "TTIPOACABTELA": "N",
      "THILOCOLO": "0",
      "TINDIANTIPILI": "1",
      "TNUMECOMP": "34",
      "TDESCCOMP": "Cu Rec(1)",
      "TTIPOCOMP": "15",
      "TDESCTIPOCOMP": "Rectilinear Neck",
      "TDESCTIPOARTI": "Cuello",
      "TFECHTENIINIC": "NaT",
      "TFECHTENIFINA": "NaT",
      "TFECHCORTINIC": "NaT",
      "TFECHCORTFINA": "NaT",
      "TFECHSECAINIC": "NaT",
      "TFECHSECAFINA": "NaT",
      "TFECHACABINIC": "NaT",
      "TFECHACABFINA": "NaT",
      "TFECHCALITINT": "NaT",
      "TFECHDESPTINT": "NaT"
    },
    {
      "TNUMEOB": 4366900,
      "TTELAPRIN": "0",
      "TTIPOARTI": "CUELLO",
      "TNUMEUD": 913666,
      "TKILOPROG": 4.987001003290606,
      "TREDUACAB": 1186707,
      "TCODITELA": "2741K",
      "TDESCTELA": "Cu-ce-g12-c3-c241p0-lm90-16 1/8 - 3 3/4",
      "TTIPOCOLN": "C",
      "TDESCTIPOCOLN": "Color entero",
      "TNUMECOLN": "73232",
      "TDESCCOLN": "Noir 031 fw24",
      "TTIPOTELA": "E",
      "TDESCTIPOTELA": "Color Entero",
      "TTIPOACABTELA": "N",
      "THILOCOLO": "0",
      "TINDIANTIPILI": "1",
      "TNUMECOMP": "34",
      "TDESCCOMP": "Cu Rec(1)",
      "TTIPOCOMP": "15",
      "TDESCTIPOCOMP": "Rectilinear Neck",
      "TDESCTIPOARTI": "Cuello",
      "TFECHTENIINIC": "NaT",
      "TFECHTENIFINA": "NaT",
      "TFECHCORTINIC": "NaT",
      "TFECHCORTFINA": "NaT",
      "TFECHSECAINIC": "NaT",
      "TFECHSECAFINA": "NaT",
      "TFECHACABINIC": "NaT",
      "TFECHACABFINA": "NaT",
      "TFECHCALITINT": "NaT",
      "TFECHDESPTINT": "NaT"
    },
    {
      "TNUMEOB": 4366901,
      "TTELAPRIN": "0",
      "TTIPOARTI": "CUELLO",
      "TNUMEUD": 913666,
      "TKILOPROG": 3.578697310676827,
      "TREDUACAB": 1186705,
      "TCODITELA": "2741K",
      "TDESCTELA": "Cu-ce-g12-c3-c241p0-lm90-16 1/8 - 3 3/4",
      "TTIPOCOLN": "C",
      "TDESCTIPOCOLN": "Color entero",
      "TNUMECOLN": "73232",
      "TDESCCOLN": "Noir 031 fw24",
      "TTIPOTELA": "E",
      "TDESCTIPOTELA": "Color Entero",
      "TTIPOACABTELA": "N",
      "THILOCOLO": "0",
      "TINDIANTIPILI": "1",
      "TNUMECOMP": "34",
      "TDESCCOMP": "Cu Rec(1)",
      "TTIPOCOMP": "15",
      "TDESCTIPOCOMP": "Rectilinear Neck",
      "TDESCTIPOARTI": "Cuello",
      "TFECHTENIINIC": "NaT",
      "TFECHTENIFINA": "NaT",
      "TFECHCORTINIC": "NaT",
      "TFECHCORTFINA": "NaT",
      "TFECHSECAINIC": "NaT",
      "TFECHSECAFINA": "NaT",
      "TFECHACABINIC": "NaT",
      "TFECHACABFINA": "NaT",
      "TFECHCALITINT": "NaT",
      "TFECHDESPTINT": "NaT"
    },
    {
      "TNUMEOB": 4366902,
      "TTELAPRIN": "0",
      "TTIPOARTI": "CUELLO",
      "TNUMEUD": 913666,
      "TKILOPROG": 3.2358024485677936,
      "TREDUACAB": 1186709,
      "TCODITELA": "2741K",
      "TDESCTELA": "Cu-ce-g12-c3-c241p0-lm90-16 1/8 - 3 3/4",
      "TTIPOCOLN": "C",
      "TDESCTIPOCOLN": "Color entero",
      "TNUMECOLN": "73232",
      "TDESCCOLN": "Noir 031 fw24",
      "TTIPOTELA": "E",
      "TDESCTIPOTELA": "Color Entero",
      "TTIPOACABTELA": "N",
      "THILOCOLO": "0",
      "TINDIANTIPILI": "1",
      "TNUMECOMP": "34",
      "TDESCCOMP": "Cu Rec(1)",
      "TTIPOCOMP": "15",
      "TDESCTIPOCOMP": "Rectilinear Neck",
      "TDESCTIPOARTI": "Cuello",
      "TFECHTENIINIC": "NaT",
      "TFECHTENIFINA": "NaT",
      "TFECHCORTINIC": "NaT",
      "TFECHCORTFINA": "NaT",
      "TFECHSECAINIC": "NaT",
      "TFECHSECAFINA": "NaT",
      "TFECHACABINIC": "NaT",
      "TFECHACABFINA": "NaT",
      "TFECHCALITINT": "NaT",
      "TFECHDESPTINT": "NaT"
    },
    {
      "TNUMEOB": 4366903,
      "TTELAPRIN": "0",
      "TTIPOARTI": "CUELLO",
      "TNUMEUD": 913666,
      "TKILOPROG": 2.352188374405751,
      "TREDUACAB": 1186708,
      "TCODITELA": "2741K",
      "TDESCTELA": "Cu-ce-g12-c3-c241p0-lm90-16 1/8 - 3 3/4",
      "TTIPOCOLN": "C",
      "TDESCTIPOCOLN": "Color entero",
      "TNUMECOLN": "73232",
      "TDESCCOLN": "Noir 031 fw24",
      "TTIPOTELA": "E",
      "TDESCTIPOTELA": "Color Entero",
      "TTIPOACABTELA": "N",
      "THILOCOLO": "0",
      "TINDIANTIPILI": "1",
      "TNUMECOMP": "34",
      "TDESCCOMP": "Cu Rec(1)",
      "TTIPOCOMP": "15",
      "TDESCTIPOCOMP": "Rectilinear Neck",
      "TDESCTIPOARTI": "Cuello",
      "TFECHTENIINIC": "NaT",
      "TFECHTENIFINA": "NaT",
      "TFECHCORTINIC": "NaT",
      "TFECHCORTFINA": "NaT",
      "TFECHSECAINIC": "NaT",
      "TFECHSECAFINA": "NaT",
      "TFECHACABINIC": "NaT",
      "TFECHACABFINA": "NaT",
      "TFECHCALITINT": "NaT",
      "TFECHDESPTINT": "NaT"
    },
    {
      "TNUMEOB": 4366898,
      "TTELAPRIN": "1",
      "TTIPOARTI": "TELA",
      "TPEDISGT": 5013773.0,
      "TNUMEUD": 913666,
      "TKILOACAB": 196.85,
      "TKILOPROG": 191.93841172044577,
      "TREDUACAB": 1194407,
      "TCODITELA": "96213",
      "TDESCTELA": "Jersey solido 24/1upland souple c/ant msuave",
      "TTIPOCOLN": "C",
      "TDESCTIPOCOLN": "Color entero",
      "TNUMECOLN": "73232",
      "TDESCCOLN": "Noir 031 fw24",
      "TTIPOTELA": "E",
      "TDESCTIPOTELA": "Color Entero",
      "TTIPOACABTELA": "N",
      "THILOCOLO": "0",
      "TINDIANTIPILI": "1",
      "TNUMECOMP": "01",
      "TDESCCOMP": "Mng(2),Splda(1),Fte(1)",
      "TTIPOCOMP": "01",
      "TDESCTIPOCOMP": "Body",
      "TDESCTIPOARTI": "Tela",
      "TMAQUTENI": "0ST32",
      "TNOMBMAQUTENI": "Saturno 32.300",
      "TMODEMAQUTENI": "Saturno.300kg",
      "TFABRMAQUTENI": "Brazzoli",
      "TPARTTINT": "194851",
      "TCODIRECE": "SL00168207",
      "TFECHTENIINIC": "2025-12-15 04:52:00",
      "TFECHTENIFINA": "2025-12-15 12:47:00",
      "TMAQUCORT": "0CO02",
      "TNOMBMAQUCORT": "Cortadora Abridora Bianco",
      "TMODEMAQUCORT": "Sdm 3512-97",
      "TFABRMAQUCORT": "Bianco",
      "TFECHCORTINIC": "2025-12-15 13:44:00",
      "TFECHCORTFINA": "2025-12-15 14:04:00",
      "TOPERCORTINIC": "E004436",
      "TNOMBOPERCORTINIC": "Cristian Pizango",
      "TMAQUSECA": "0SE02",
      "TNOMBMAQUSECA": "Secadora Relaxa 2",
      "TMODEMAQUSECA": "Relaxa",
      "TFABRMAQUSECA": "Sperotto",
      "TFECHSECAINIC": "2025-12-15 15:27:00",
      "TFECHSECAFINA": "2025-12-15 16:27:00",
      "TOPERSECAINIC": "E003775",
      "TNOMBOPERSECAINIC": "Anibal Cordova",
      "TMAQUACAB": "0RM03",
      "TNOMBMAQUACAB": "Rama 3",
      "TMODEMAQUACAB": "Red Evo 5",
      "TFABRMAQUACAB": "Unitech",
      "TFECHACABINIC": "2025-12-17 21:15:00",
      "TFECHACABFINA": "2025-12-17 22:00:00",
      "TOPERACABINIC": "E004598",
      "TNOMBOPERACABINIC": "Noe Ayala",
      "TFECHCALITINT": "2025-12-17 19:53:00",
      "TFECHDESPTINT": "2025-12-19 00:00:00"
    },
    {
      "TNUMEOB": 4366904,
      "TTELAPRIN": "0",
      "TTIPOARTI": "PUÑO",
      "TNUMEUD": 913666,
      "TKILOPROG": 3.5311703131657772,
      "TREDUACAB": 1194417,
      "TCODITELA": "5912K",
      "TDESCTELA": "Pu-ce-g12-c3-c241p0-l140a0-2-lm90-32 7/8 - 1 3/16",
      "TTIPOCOLN": "C",
      "TDESCTIPOCOLN": "Color entero",
      "TNUMECOLN": "73232",
      "TDESCCOLN": "Noir 031 fw24",
      "TTIPOTELA": "E",
      "TDESCTIPOTELA": "Color Entero",
      "TTIPOACABTELA": "N",
      "THILOCOLO": "0",
      "TINDIANTIPILI": "1",
      "TNUMECOMP": "37",
      "TDESCCOMP": "Pu Rec(2)",
      "TTIPOCOMP": "16",
      "TDESCTIPOCOMP": "Wristband",
      "TDESCTIPOARTI": "Puño",
      "TFECHTENIINIC": "NaT",
      "TFECHTENIFINA": "NaT",
      "TFECHCORTINIC": "NaT",
      "TFECHCORTFINA": "NaT",
      "TFECHSECAINIC": "NaT",
      "TFECHSECAFINA": "NaT",
      "TFECHACABINIC": "NaT",
      "TFECHACABFINA": "NaT",
      "TFECHCALITINT": "NaT",
      "TFECHDESPTINT": "NaT"
    },
    {
      "TNUMEOB": 4366905,
      "TTELAPRIN": "0",
      "TTIPOARTI": "PUÑO",
      "TNUMEUD": 913666,
      "TKILOPROG": 3.458318901396046,
      "TREDUACAB": 1194445,
      "TCODITELA": "5912K",
      "TDESCTELA": "Pu-ce-g12-c3-c241p0-l140a0-2-lm90-32 7/8 - 1 3/16",
      "TTIPOCOLN": "C",
      "TDESCTIPOCOLN": "Color entero",
      "TNUMECOLN": "73232",
      "TDESCCOLN": "Noir 031 fw24",
      "TTIPOTELA": "E",
      "TDESCTIPOTELA": "Color Entero",
      "TTIPOACABTELA": "N",
      "THILOCOLO": "0",
      "TINDIANTIPILI": "1",
      "TNUMECOMP": "37",
      "TDESCCOMP": "Pu Rec(2)",
      "TTIPOCOMP": "16",
      "TDESCTIPOCOMP": "Wristband",
      "TDESCTIPOARTI": "Puño",
      "TFECHTENIINIC": "NaT",
      "TFECHTENIFINA": "NaT",
      "TFECHCORTINIC": "NaT",
      "TFECHCORTFINA": "NaT",
      "TFECHSECAINIC": "NaT",
      "TFECHSECAFINA": "NaT",
      "TFECHACABINIC": "NaT",
      "TFECHACABFINA": "NaT",
      "TFECHCALITINT": "NaT",
      "TFECHDESPTINT": "NaT"
    },
    {
      "TNUMEOB": 4366906,
      "TTELAPRIN": "0",
      "TTIPOARTI": "PUÑO",
      "TNUMEUD": 913666,
      "TKILOPROG": 2.92637560869832,
      "TREDUACAB": 1194446,
      "TCODITELA": "5912K",
      "TDESCTELA": "Pu-ce-g12-c3-c241p0-l140a0-2-lm90-32 7/8 - 1 3/16",
      "TTIPOCOLN": "C",
      "TDESCTIPOCOLN": "Color entero",
      "TNUMECOLN": "73232",
      "TDESCCOLN": "Noir 031 fw24",
      "TTIPOTELA": "E",
      "TDESCTIPOTELA": "Color Entero",
      "TTIPOACABTELA": "N",
      "THILOCOLO": "0",
      "TINDIANTIPILI": "1",
      "TNUMECOMP": "37",
      "TDESCCOMP": "Pu Rec(2)",
      "TTIPOCOMP": "16",
      "TDESCTIPOCOMP": "Wristband",
      "TDESCTIPOARTI": "Puño",
      "TFECHTENIINIC": "NaT",
      "TFECHTENIFINA": "NaT",
      "TFECHCORTINIC": "NaT",
      "TFECHCORTFINA": "NaT",
      "TFECHSECAINIC": "NaT",
      "TFECHSECAFINA": "NaT",
      "TFECHACABINIC": "NaT",
      "TFECHACABFINA": "NaT",
      "TFECHCALITINT": "NaT",
      "TFECHDESPTINT": "NaT"
    },
    {
      "TNUMEOB": 4366907,
      "TTELAPRIN": "0",
      "TTIPOARTI": "PUÑO",
      "TNUMEUD": 913666,
      "TKILOPROG": 1.5602447237162387,
      "TREDUACAB": 1194444,
      "TCODITELA": "5912K",
      "TDESCTELA": "Pu-ce-g12-c3-c241p0-l140a0-2-lm90-32 7/8 - 1 3/16",
      "TTIPOCOLN": "C",
      "TDESCTIPOCOLN": "Color entero",
      "TNUMECOLN": "73232",
      "TDESCCOLN": "Noir 031 fw24",
      "TTIPOTELA": "E",
      "TDESCTIPOTELA": "Color Entero",
      "TTIPOACABTELA": "N",
      "THILOCOLO": "0",
      "TINDIANTIPILI": "1",
      "TNUMECOMP": "37",
      "TDESCCOMP": "Pu Rec(2)",
      "TTIPOCOMP": "16",
      "TDESCTIPOCOMP": "Wristband",
      "TDESCTIPOARTI": "Puño",
      "TFECHTENIINIC": "NaT",
      "TFECHTENIFINA": "NaT",
      "TFECHCORTINIC": "NaT",
      "TFECHCORTFINA": "NaT",
      "TFECHSECAINIC": "NaT",
      "TFECHSECAFINA": "NaT",
      "TFECHACABINIC": "NaT",
      "TFECHACABFINA": "NaT",
      "TFECHCALITINT": "NaT",
      "TFECHDESPTINT": "NaT"
    },
    {
      "TNUMEOB": 4366908,
      "TTELAPRIN": "0",
      "TTIPOARTI": "PUÑO",
      "TNUMEUD": 913666,
      "TKILOPROG": 1.3709364440372362,
      "TREDUACAB": 1194447,
      "TCODITELA": "5912K",
      "TDESCTELA": "Pu-ce-g12-c3-c241p0-l140a0-2-lm90-32 7/8 - 1 3/16",
      "TTIPOCOLN": "C",
      "TDESCTIPOCOLN": "Color entero",
      "TNUMECOLN": "73232",
      "TDESCCOLN": "Noir 031 fw24",
      "TTIPOTELA": "E",
      "TDESCTIPOTELA": "Color Entero",
      "TTIPOACABTELA": "N",
      "THILOCOLO": "0",
      "TINDIANTIPILI": "1",
      "TNUMECOMP": "37",
      "TDESCCOMP": "Pu Rec(2)",
      "TTIPOCOMP": "16",
      "TDESCTIPOCOMP": "Wristband",
      "TDESCTIPOARTI": "Puño",
      "TFECHTENIINIC": "NaT",
      "TFECHTENIFINA": "NaT",
      "TFECHCORTINIC": "NaT",
      "TFECHCORTFINA": "NaT",
      "TFECHSECAINIC": "NaT",
      "TFECHSECAFINA": "NaT",
      "TFECHACABINIC": "NaT",
      "TFECHACABFINA": "NaT",
      "TFECHCALITINT": "NaT",
      "TFECHDESPTINT": "NaT"
    },
    {
      "TNUMEOB": 4366909,
      "TTELAPRIN": "0",
      "TTIPOARTI": "PUÑO",
      "TNUMEUD": 913666,
      "TKILOPROG": 1.2592866829581102,
      "TREDUACAB": 1194448,
      "TCODITELA": "5912K",
      "TDESCTELA": "Pu-ce-g12-c3-c241p0-l140a0-2-lm90-32 7/8 - 1 3/16",
      "TTIPOCOLN": "C",
      "TDESCTIPOCOLN": "Color entero",
      "TNUMECOLN": "73232",
      "TDESCCOLN": "Noir 031 fw24",
      "TTIPOTELA": "E",
      "TDESCTIPOTELA": "Color Entero",
      "TTIPOACABTELA": "N",
      "THILOCOLO": "0",
      "TINDIANTIPILI": "1",
      "TNUMECOMP": "37",
      "TDESCCOMP": "Pu Rec(2)",
      "TTIPOCOMP": "16",
      "TDESCTIPOCOMP": "Wristband",
      "TDESCTIPOARTI": "Puño",
      "TFECHTENIINIC": "NaT",
      "TFECHTENIFINA": "NaT",
      "TFECHCORTINIC": "NaT",
      "TFECHCORTFINA": "NaT",
      "TFECHSECAINIC": "NaT",
      "TFECHSECAFINA": "NaT",
      "TFECHACABINIC": "NaT",
      "TFECHACABFINA": "NaT",
      "TFECHCALITINT": "NaT",
      "TFECHDESPTINT": "NaT"
    },
    {
      "TNUMEOB": 4366910,
      "TTELAPRIN": "0",
      "TTIPOARTI": "PUÑO",
      "TNUMEUD": 913666,
      "TKILOPROG": 0.6680343773812717,
      "TREDUACAB": 1194449,
      "TCODITELA": "5912K",
      "TDESCTELA": "Pu-ce-g12-c3-c241p0-l140a0-2-lm90-32 7/8 - 1 3/16",
      "TTIPOCOLN": "C",
      "TDESCTIPOCOLN": "Color entero",
      "TNUMECOLN": "73232",
      "TDESCCOLN": "Noir 031 fw24",
      "TTIPOTELA": "E",
      "TDESCTIPOTELA": "Color Entero",
      "TTIPOACABTELA": "N",
      "THILOCOLO": "0",
      "TINDIANTIPILI": "1",
      "TNUMECOMP": "37",
      "TDESCCOMP": "Pu Rec(2)",
      "TTIPOCOMP": "16",
      "TDESCTIPOCOMP": "Wristband",
      "TDESCTIPOARTI": "Puño",
      "TFECHTENIINIC": "NaT",
      "TFECHTENIFINA": "NaT",
      "TFECHCORTINIC": "NaT",
      "TFECHCORTFINA": "NaT",
      "TFECHSECAINIC": "NaT",
      "TFECHSECAFINA": "NaT",
      "TFECHACABINIC": "NaT",
      "TFECHACABFINA": "NaT",
      "TFECHCALITINT": "NaT",
      "TFECHDESPTINT": "NaT"
    },
    {
      "TNUMEOB": 4366911,
      "TTELAPRIN": "0",
      "TTIPOARTI": "PUÑO",
      "TNUMEUD": 913666,
      "TKILOPROG": 0.4958454875559963,
      "TREDUACAB": 1194443,
      "TCODITELA": "5912K",
      "TDESCTELA": "Pu-ce-g12-c3-c241p0-l140a0-2-lm90-32 7/8 - 1 3/16",
      "TTIPOCOLN": "C",
      "TDESCTIPOCOLN": "Color entero",
      "TNUMECOLN": "73232",
      "TDESCCOLN": "Noir 031 fw24",
      "TTIPOTELA": "E",
      "TDESCTIPOTELA": "Color Entero",
      "TTIPOACABTELA": "N",
      "THILOCOLO": "0",
      "TINDIANTIPILI": "1",
      "TNUMECOMP": "37",
      "TDESCCOMP": "Pu Rec(2)",
      "TTIPOCOMP": "16",
      "TDESCTIPOCOMP": "Wristband",
      "TDESCTIPOARTI": "Puño",
      "TFECHTENIINIC": "NaT",
      "TFECHTENIFINA": "NaT",
      "TFECHCORTINIC": "NaT",
      "TFECHCORTFINA": "NaT",
      "TFECHSECAINIC": "NaT",
      "TFECHSECAFINA": "NaT",
      "TFECHACABINIC": "NaT",
      "TFECHACABFINA": "NaT",
      "TFECHCALITINT": "NaT",
      "TFECHDESPTINT": "NaT"
    }
  ],
  "tztotrazwebteje": [
    {
      "TORDETEJE": 1090597,
      "TTELAPRIN": "0",
      "TNUMEOB": 4366899,
      "TREDUCRUD": 1072252,
      "TCODITELA": "2741K",
      "TDESCTELA": "Cu-ce-g12-c3-c241p0-lm90-16 1/8 - 3 3/4",
      "TNUMEGALG": 12,
      "TDESCTIPOARTI": "Cuello",
      "THILOCOLO": "0",
      "TTIPOTEJI": "C",
      "TDESCTIPOTEJI": "Rectilineos",
      "TTIPOMAQUTEJE": "N",
      "TDESCTIPOMAQUTEJE": "Rectilineos",
      "TCODIMATEPRIM": "E",
      "TDESCCODIMATEPRIM": "Mezcla Pima Peruano - Pima Americano",
      "TMATEPRIM": "B",
      "TDESCMATEPRIM": "Algodon Tanguis",
      "TNUMEPIEZ": 4257353,
      "TSECUPIEZ": 0,
      "TFECHTEJE": "2025-11-11 17:37:00",
      "TCALIPIEZ": 1,
      "TDESCCALI": "1a Calidad",
      "TKILOPIEZ": 2.477,
      "TMETRPIEZ": 0.99,
      "TCODIMAQU": "0R032",
      "TNOMBMAQU": "Matsuya 32 G16 F40",
      "TMODEMAQU": "Matsuya",
      "TFABRMAQU": "Matsuya",
      "TRPMSTND": 34.0,
      "TCODIPERS": "E004557",
      "TNOMBPERS": "Alwin Lachuma"
    },
    {
      "TORDETEJE": 1092140,
      "TTELAPRIN": "0",
      "TNUMEOB": 4366899,
      "TREDUCRUD": 1072252,
      "TCODITELA": "2741K",
      "TDESCTELA": "Cu-ce-g12-c3-c241p0-lm90-16 1/8 - 3 3/4",
      "TNUMEGALG": 12,
      "TDESCTIPOARTI": "Cuello",
      "THILOCOLO": "0",
      "TTIPOTEJI": "C",
      "TDESCTIPOTEJI": "Rectilineos",
      "TTIPOMAQUTEJE": "N",
      "TDESCTIPOMAQUTEJE": "Rectilineos",
      "TCODIMATEPRIM": "E",
      "TDESCCODIMATEPRIM": "Mezcla Pima Peruano - Pima Americano",
      "TMATEPRIM": "B",
      "TDESCMATEPRIM": "Algodon Tanguis",
      "TNUMEPIEZ": 4262716,
      "TSECUPIEZ": 0,
      "TFECHTEJE": "2025-12-08 01:56:00",
      "TCALIPIEZ": 1,
      "TDESCCALI": "1a Calidad",
      "TKILOPIEZ": 0.625,
      "TMETRPIEZ": 0.238,
      "TCODIMAQU": "0R0A7",
      "TNOMBMAQU": "Protti A7 G12 F86",
      "TMODEMAQU": "Protti",
      "TFABRMAQU": "Protti",
      "TRPMSTND": 18.0,
      "TCODIPERS": "E004274",
      "TNOMBPERS": "Teofilo Rodriguez"
    },
    {
      "TORDETEJE": 1089437,
      "TTELAPRIN": "0",
      "TNUMEOB": 4366899,
      "TREDUCRUD": 1072252,
      "TCODITELA": "2741K",
      "TDESCTELA": "Cu-ce-g12-c3-c241p0-lm90-16 1/8 - 3 3/4",
      "TNUMEGALG": 12,
      "TDESCTIPOARTI": "Cuello",
      "THILOCOLO": "0",
      "TTIPOTEJI": "C",
      "TDESCTIPOTEJI": "Rectilineos",
      "TTIPOMAQUTEJE": "N",
      "TDESCTIPOMAQUTEJE": "Rectilineos",
      "TCODIMATEPRIM": "E",
      "TDESCCODIMATEPRIM": "Mezcla Pima Peruano - Pima Americano",
      "TMATEPRIM": "B",
      "TDESCMATEPRIM": "Algodon Tanguis",
      "TNUMEPIEZ": 4253116,
      "TSECUPIEZ": 2,
      "TFECHTEJE": "2025-11-04 12:12:00",
      "TCALIPIEZ": 1,
      "TDESCCALI": "1a Calidad",
      "TKILOPIEZ": 1.408,
      "TMETRPIEZ": 0.609,
      "TCODIMAQU": "0RA17",
      "TNOMBMAQU": "Protti A12 G12 F86",
      "TMODEMAQU": "Pt22j",
      "TFABRMAQU": "Protti",
      "TRPMSTND": 18.0,
      "TCODIPERS": "E004520",
      "TNOMBPERS": "Jhack Campojo"
    },
    {
      "TORDETEJE": 1090597,
      "TTELAPRIN": "0",
      "TNUMEOB": 4366899,
      "TREDUCRUD": 1072252,
      "TCODITELA": "2741K",
      "TDESCTELA": "Cu-ce-g12-c3-c241p0-lm90-16 1/8 - 3 3/4",
      "TNUMEGALG": 12,
      "TDESCTIPOARTI": "Cuello",
      "THILOCOLO": "0",
      "TTIPOTEJI": "C",
      "TDESCTIPOTEJI": "Rectilineos",
      "TTIPOMAQUTEJE": "N",
      "TDESCTIPOMAQUTEJE": "Rectilineos",
      "TCODIMATEPRIM": "E",
      "TDESCCODIMATEPRIM": "Mezcla Pima Peruano - Pima Americano",
      "TMATEPRIM": "B",
      "TDESCMATEPRIM": "Algodon Tanguis",
      "TNUMEPIEZ": 4257354,
      "TSECUPIEZ": 0,
      "TFECHTEJE": "2025-11-11 17:38:00",
      "TCALIPIEZ": 1,
      "TDESCCALI": "1a Calidad",
      "TKILOPIEZ": 7.4,
      "TMETRPIEZ": 2.858,
      "TCODIMAQU": "0R032",
      "TNOMBMAQU": "Matsuya 32 G16 F40",
      "TMODEMAQU": "Matsuya",
      "TFABRMAQU": "Matsuya",
      "TRPMSTND": 34.0,
      "TCODIPERS": "E004557",
      "TNOMBPERS": "Alwin Lachuma"
    },
    {
      "TORDETEJE": 1090316,
      "TTELAPRIN": "0",
      "TNUMEOB": 4366900,
      "TREDUCRUD": 1092168,
      "TCODITELA": "2741K",
      "TDESCTELA": "Cu-ce-g12-c3-c241p0-lm90-16 1/8 - 3 3/4",
      "TNUMEGALG": 12,
      "TDESCTIPOARTI": "Cuello",
      "THILOCOLO": "0",
      "TTIPOTEJI": "C",
      "TDESCTIPOTEJI": "Rectilineos",
      "TTIPOMAQUTEJE": "N",
      "TDESCTIPOMAQUTEJE": "Rectilineos",
      "TCODIMATEPRIM": "E",
      "TDESCCODIMATEPRIM": "Mezcla Pima Peruano - Pima Americano",
      "TMATEPRIM": "B",
      "TDESCMATEPRIM": "Algodon Tanguis",
      "TNUMEPIEZ": 4256180,
      "TSECUPIEZ": 0,
      "TFECHTEJE": "2025-11-08 16:22:00",
      "TCALIPIEZ": 1,
      "TDESCCALI": "1a Calidad",
      "TKILOPIEZ": 2.083,
      "TMETRPIEZ": 0.781,
      "TCODIMAQU": "0R031",
      "TNOMBMAQU": "Matsuya 31 G16 F40",
      "TMODEMAQU": "Matsuya",
      "TFABRMAQU": "Matsuya",
      "TRPMSTND": 34.0,
      "TCODIPERS": "E004595",
      "TNOMBPERS": "Jose Mozombite"
    },
    {
      "TORDETEJE": 1089303,
      "TTELAPRIN": "0",
      "TNUMEOB": 4366900,
      "TREDUCRUD": 1092168,
      "TCODITELA": "2741K",
      "TDESCTELA": "Cu-ce-g12-c3-c241p0-lm90-16 1/8 - 3 3/4",
      "TNUMEGALG": 12,
      "TDESCTIPOARTI": "Cuello",
      "THILOCOLO": "0",
      "TTIPOTEJI": "C",
      "TDESCTIPOTEJI": "Rectilineos",
      "TTIPOMAQUTEJE": "N",
      "TDESCTIPOMAQUTEJE": "Rectilineos",
      "TCODIMATEPRIM": "E",
      "TDESCCODIMATEPRIM": "Mezcla Pima Peruano - Pima Americano",
      "TMATEPRIM": "B",
      "TDESCMATEPRIM": "Algodon Tanguis",
      "TNUMEPIEZ": 4252901,
      "TSECUPIEZ": 0,
      "TFECHTEJE": "2025-10-25 05:28:00",
      "TCALIPIEZ": 1,
      "TDESCCALI": "1a Calidad",
      "TKILOPIEZ": 1.276,
      "TMETRPIEZ": 0.429,
      "TCODIMAQU": "0R014",
      "TNOMBMAQU": "Matsuya 14 G16 F40",
      "TMODEMAQU": "Matsuya",
      "TFABRMAQU": "Matsuya",
      "TRPMSTND": 34.0,
      "TCODIPERS": "E004595",
      "TNOMBPERS": "Jose Mozombite"
    },
    {
      "TORDETEJE": 1085631,
      "TTELAPRIN": "0",
      "TNUMEOB": 4366900,
      "TREDUCRUD": 1092168,
      "TCODITELA": "2741K",
      "TDESCTELA": "Cu-ce-g12-c3-c241p0-lm90-16 1/8 - 3 3/4",
      "TNUMEGALG": 12,
      "TDESCTIPOARTI": "Cuello",
      "THILOCOLO": "0",
      "TTIPOTEJI": "C",
      "TDESCTIPOTEJI": "Rectilineos",
      "TTIPOMAQUTEJE": "N",
      "TDESCTIPOMAQUTEJE": "Rectilineos",
      "TCODIMATEPRIM": "E",
      "TDESCCODIMATEPRIM": "Mezcla Pima Peruano - Pima Americano",
      "TMATEPRIM": "B",
      "TDESCMATEPRIM": "Algodon Tanguis",
      "TNUMEPIEZ": 4238977,
      "TSECUPIEZ": 0,
      "TFECHTEJE": "2025-09-16 03:18:00",
      "TCALIPIEZ": 1,
      "TDESCCALI": "1a Calidad",
      "TKILOPIEZ": 1.802,
      "TMETRPIEZ": 0.657,
      "TCODIMAQU": "0R027",
      "TNOMBMAQU": "Matsuya 27 G16 F40",
      "TMODEMAQU": "Matsuya",
      "TFABRMAQU": "Matsuya",
      "TRPMSTND": 34.0,
      "TCODIPERS": "E00D232",
      "TNOMBPERS": "Victor Huaman"
    },
    {
      "TORDETEJE": 1090227,
      "TTELAPRIN": "0",
      "TNUMEOB": 4366900,
      "TREDUCRUD": 1092168,
      "TCODITELA": "2741K",
      "TDESCTELA": "Cu-ce-g12-c3-c241p0-lm90-16 1/8 - 3 3/4",
      "TNUMEGALG": 12,
      "TDESCTIPOARTI": "Cuello",
      "THILOCOLO": "0",
      "TTIPOTEJI": "C",
      "TDESCTIPOTEJI": "Rectilineos",
      "TTIPOMAQUTEJE": "N",
      "TDESCTIPOMAQUTEJE": "Rectilineos",
      "TCODIMATEPRIM": "E",
      "TDESCCODIMATEPRIM": "Mezcla Pima Peruano - Pima Americano",
      "TMATEPRIM": "B",
      "TDESCMATEPRIM": "Algodon Tanguis",
      "TNUMEPIEZ": 4255934,
      "TSECUPIEZ": 3,
      "TFECHTEJE": "2025-11-04 20:42:00",
      "TCALIPIEZ": 1,
      "TDESCCALI": "1a Calidad",
      "TKILOPIEZ": 0.311,
      "TMETRPIEZ": 0.114,
      "TCODIMAQU": "0R014",
      "TNOMBMAQU": "Matsuya 14 G16 F40",
      "TMODEMAQU": "Matsuya",
      "TFABRMAQU": "Matsuya",
      "TRPMSTND": 34.0,
      "TCODIPERS": "E00D232",
      "TNOMBPERS": "Victor Huaman"
    },
    {
      "TORDETEJE": 1092522,
      "TTELAPRIN": "0",
      "TNUMEOB": 4366901,
      "TREDUCRUD": 1092167,
      "TCODITELA": "2741K",
      "TDESCTELA": "Cu-ce-g12-c3-c241p0-lm90-16 1/8 - 3 3/4",
      "TNUMEGALG": 12,
      "TDESCTIPOARTI": "Cuello",
      "THILOCOLO": "0",
      "TTIPOTEJI": "C",
      "TDESCTIPOTEJI": "Rectilineos",
      "TTIPOMAQUTEJE": "N",
      "TDESCTIPOMAQUTEJE": "Rectilineos",
      "TCODIMATEPRIM": "E",
      "TDESCCODIMATEPRIM": "Mezcla Pima Peruano - Pima Americano",
      "TMATEPRIM": "B",
      "TDESCMATEPRIM": "Algodon Tanguis",
      "TNUMEPIEZ": 4264397,
      "TSECUPIEZ": 0,
      "TFECHTEJE": "2025-12-11 20:53:00",
      "TCALIPIEZ": 1,
      "TDESCCALI": "1a Calidad",
      "TKILOPIEZ": 2.95,
      "TMETRPIEZ": 1.476,
      "TCODIMAQU": "0RA12",
      "TNOMBMAQU": "Protti A12 G12 F86",
      "TMODEMAQU": "Pt22j",
      "TFABRMAQU": "Protti",
      "TRPMSTND": 18.0,
      "TCODIPERS": "E004520",
      "TNOMBPERS": "Jhack Campojo"
    },
    {
      "TORDETEJE": 1090124,
      "TTELAPRIN": "0",
      "TNUMEOB": 4366901,
      "TREDUCRUD": 1092167,
      "TCODITELA": "2741K",
      "TDESCTELA": "Cu-ce-g12-c3-c241p0-lm90-16 1/8 - 3 3/4",
      "TNUMEGALG": 12,
      "TDESCTIPOARTI": "Cuello",
      "THILOCOLO": "0",
      "TTIPOTEJI": "C",
      "TDESCTIPOTEJI": "Rectilineos",
      "TTIPOMAQUTEJE": "N",
      "TDESCTIPOMAQUTEJE": "Rectilineos",
      "TCODIMATEPRIM": "E",
      "TDESCCODIMATEPRIM": "Mezcla Pima Peruano - Pima Americano",
      "TMATEPRIM": "B",
      "TDESCMATEPRIM": "Algodon Tanguis",
      "TNUMEPIEZ": 4255363,
      "TSECUPIEZ": 3,
      "TFECHTEJE": "2025-11-03 08:39:00",
      "TCALIPIEZ": 1,
      "TDESCCALI": "1a Calidad",
      "TKILOPIEZ": 0.255,
      "TMETRPIEZ": 0.114,
      "TCODIMAQU": "0R020",
      "TNOMBMAQU": "Matsuya 20 G12 F40",
      "TMODEMAQU": "Matsuya",
      "TFABRMAQU": "Matsuya",
      "TRPMSTND": 34.0,
      "TCODIPERS": "E004595",
      "TNOMBPERS": "Jose Mozombite"
    },
    {
      "TORDETEJE": 1090229,
      "TTELAPRIN": "0",
      "TNUMEOB": 4366902,
      "TREDUCRUD": 1092170,
      "TCODITELA": "2741K",
      "TDESCTELA": "Cu-ce-g12-c3-c241p0-lm90-16 1/8 - 3 3/4",
      "TNUMEGALG": 12,
      "TDESCTIPOARTI": "Cuello",
      "THILOCOLO": "0",
      "TTIPOTEJI": "C",
      "TDESCTIPOTEJI": "Rectilineos",
      "TTIPOMAQUTEJE": "N",
      "TDESCTIPOMAQUTEJE": "Rectilineos",
      "TCODIMATEPRIM": "E",
      "TDESCCODIMATEPRIM": "Mezcla Pima Peruano - Pima Americano",
      "TMATEPRIM": "B",
      "TDESCMATEPRIM": "Algodon Tanguis",
      "TNUMEPIEZ": 4255953,
      "TSECUPIEZ": 0,
      "TFECHTEJE": "2025-11-05 14:39:00",
      "TCALIPIEZ": 1,
      "TDESCCALI": "1a Calidad",
      "TKILOPIEZ": 0.814,
      "TMETRPIEZ": 0.29,
      "TCODIMAQU": "0R0A4",
      "TNOMBMAQU": "Matsuya A4 G16 F40",
      "TMODEMAQU": "Matsuya",
      "TFABRMAQU": "Matsuya",
      "TRPMSTND": 34.0,
      "TCODIPERS": "E004595",
      "TNOMBPERS": "Jose Mozombite"
    },
    {
      "TORDETEJE": 1090069,
      "TTELAPRIN": "0",
      "TNUMEOB": 4366902,
      "TREDUCRUD": 1092170,
      "TCODITELA": "2741K",
      "TDESCTELA": "Cu-ce-g12-c3-c241p0-lm90-16 1/8 - 3 3/4",
      "TNUMEGALG": 12,
      "TDESCTIPOARTI": "Cuello",
      "THILOCOLO": "0",
      "TTIPOTEJI": "C",
      "TDESCTIPOTEJI": "Rectilineos",
      "TTIPOMAQUTEJE": "N",
      "TDESCTIPOMAQUTEJE": "Rectilineos",
      "TCODIMATEPRIM": "E",
      "TDESCCODIMATEPRIM": "Mezcla Pima Peruano - Pima Americano",
      "TMATEPRIM": "B",
      "TDESCMATEPRIM": "Algodon Tanguis",
      "TNUMEPIEZ": 4255000,
      "TSECUPIEZ": 0,
      "TFECHTEJE": "2025-11-01 10:18:00",
      "TCALIPIEZ": 1,
      "TDESCCALI": "1a Calidad",
      "TKILOPIEZ": 1.879,
      "TMETRPIEZ": 0.65,
      "TCODIMAQU": "0R014",
      "TNOMBMAQU": "Matsuya 14 G16 F40",
      "TMODEMAQU": "Matsuya",
      "TFABRMAQU": "Matsuya",
      "TRPMSTND": 34.0,
      "TCODIPERS": "E004431",
      "TNOMBPERS": "Juesman Angulo"
    },
    {
      "TORDETEJE": 1090069,
      "TTELAPRIN": "0",
      "TNUMEOB": 4366902,
      "TREDUCRUD": 1092170,
      "TCODITELA": "2741K",
      "TDESCTELA": "Cu-ce-g12-c3-c241p0-lm90-16 1/8 - 3 3/4",
      "TNUMEGALG": 12,
      "TDESCTIPOARTI": "Cuello",
      "THILOCOLO": "0",
      "TTIPOTEJI": "C",
      "TDESCTIPOTEJI": "Rectilineos",
      "TTIPOMAQUTEJE": "N",
      "TDESCTIPOMAQUTEJE": "Rectilineos",
      "TCODIMATEPRIM": "E",
      "TDESCCODIMATEPRIM": "Mezcla Pima Peruano - Pima Americano",
      "TMATEPRIM": "B",
      "TDESCMATEPRIM": "Algodon Tanguis",
      "TNUMEPIEZ": 4254999,
      "TSECUPIEZ": 0,
      "TFECHTEJE": "2025-10-31 18:52:00",
      "TCALIPIEZ": 1,
      "TDESCCALI": "1a Calidad",
      "TKILOPIEZ": 0.72,
      "TMETRPIEZ": 0.25,
      "TCODIMAQU": "0R014",
      "TNOMBMAQU": "Matsuya 14 G16 F40",
      "TMODEMAQU": "Matsuya",
      "TFABRMAQU": "Matsuya",
      "TRPMSTND": 34.0,
      "TCODIPERS": "E004520",
      "TNOMBPERS": "Jhack Campojo"
    },
    {
      "TORDETEJE": 1092168,
      "TTELAPRIN": "0",
      "TNUMEOB": 4366903,
      "TREDUCRUD": 1092169,
      "TCODITELA": "2741K",
      "TDESCTELA": "Cu-ce-g12-c3-c241p0-lm90-16 1/8 - 3 3/4",
      "TNUMEGALG": 12,
      "TDESCTIPOARTI": "Cuello",
      "THILOCOLO": "0",
      "TTIPOTEJI": "C",
      "TDESCTIPOTEJI": "Rectilineos",
      "TTIPOMAQUTEJE": "N",
      "TDESCTIPOMAQUTEJE": "Rectilineos",
      "TCODIMATEPRIM": "E",
      "TDESCCODIMATEPRIM": "Mezcla Pima Peruano - Pima Americano",
      "TMATEPRIM": "B",
      "TDESCMATEPRIM": "Algodon Tanguis",
      "TNUMEPIEZ": 4262823,
      "TSECUPIEZ": 3,
      "TFECHTEJE": "2025-12-09 05:38:00",
      "TCALIPIEZ": 1,
      "TDESCCALI": "1a Calidad",
      "TKILOPIEZ": 1.249,
      "TMETRPIEZ": 0.47,
      "TCODIMAQU": "0R0A7",
      "TNOMBMAQU": "Protti A7 G12 F86",
      "TMODEMAQU": "Protti",
      "TFABRMAQU": "Protti",
      "TRPMSTND": 18.0,
      "TCODIPERS": "E004274",
      "TNOMBPERS": "Teofilo Rodriguez"
    },
    {
      "TORDETEJE": 1089873,
      "TTELAPRIN": "0",
      "TNUMEOB": 4366903,
      "TREDUCRUD": 1092169,
      "TCODITELA": "2741K",
      "TDESCTELA": "Cu-ce-g12-c3-c241p0-lm90-16 1/8 - 3 3/4",
      "TNUMEGALG": 12,
      "TDESCTIPOARTI": "Cuello",
      "THILOCOLO": "0",
      "TTIPOTEJI": "C",
      "TDESCTIPOTEJI": "Rectilineos",
      "TTIPOMAQUTEJE": "N",
      "TDESCTIPOMAQUTEJE": "Rectilineos",
      "TCODIMATEPRIM": "E",
      "TDESCCODIMATEPRIM": "Mezcla Pima Peruano - Pima Americano",
      "TMATEPRIM": "B",
      "TDESCMATEPRIM": "Algodon Tanguis",
      "TNUMEPIEZ": 4254759,
      "TSECUPIEZ": 0,
      "TFECHTEJE": "2025-10-31 16:51:00",
      "TCALIPIEZ": 1,
      "TDESCCALI": "1a Calidad",
      "TKILOPIEZ": 1.217,
      "TMETRPIEZ": 0.44,
      "TCODIMAQU": "0R032",
      "TNOMBMAQU": "Matsuya 32 G16 F40",
      "TMODEMAQU": "Matsuya",
      "TFABRMAQU": "Matsuya",
      "TRPMSTND": 34.0,
      "TCODIPERS": "E003015",
      "TNOMBPERS": "Vicente Chavez"
    },
    {
      "TORDETEJE": 1091773,
      "TTELAPRIN": "1",
      "TKILOCRUD": 199.62,
      "TNUMEOB": 4366898,
      "TREDUCRUD": 815353,
      "TCODITELA": "96213",
      "TDESCTELA": "Jersey solido 24/1upland souple c/ant msuave",
      "TNUMEGALG": 28,
      "TDESCTIPOARTI": "Tela",
      "THILOCOLO": "0",
      "TTIPOTEJI": "J",
      "TDESCTIPOTEJI": "Jersey",
      "TTIPOMAQUTEJE": "T",
      "TDESCTIPOMAQUTEJE": "Circular",
      "TCODIMATEPRIM": "E",
      "TDESCCODIMATEPRIM": "Mezcla Pima Peruano - Pima Americano",
      "TMATEPRIM": "B",
      "TDESCMATEPRIM": "Algodon Tanguis",
      "TNUMEPIEZ": 4264913,
      "TSECUPIEZ": 0,
      "TFECHTEJE": "2025-12-13 18:11:00",
      "TCALIPIEZ": 1,
      "TDESCCALI": "1a Calidad",
      "TKILOPIEZ": 32.4,
      "TMETRPIEZ": 99.606,
      "TCODIMAQU": "0C0L5",
      "TNOMBMAQU": "Jersera L5 D30 96a",
      "TMODEMAQU": "S296-1",
      "TFABRMAQU": "Terrot",
      "TRPMSTND": 28.0,
      "TCODIPERS": "E003137",
      "TNOMBPERS": "John Cruz"
    },
    {
      "TORDETEJE": 1091773,
      "TTELAPRIN": "1",
      "TKILOCRUD": 199.62,
      "TNUMEOB": 4366898,
      "TREDUCRUD": 815353,
      "TCODITELA": "96213",
      "TDESCTELA": "Jersey solido 24/1upland souple c/ant msuave",
      "TNUMEGALG": 28,
      "TDESCTIPOARTI": "Tela",
      "THILOCOLO": "0",
      "TTIPOTEJI": "J",
      "TDESCTIPOTEJI": "Jersey",
      "TTIPOMAQUTEJE": "T",
      "TDESCTIPOMAQUTEJE": "Circular",
      "TCODIMATEPRIM": "E",
      "TDESCCODIMATEPRIM": "Mezcla Pima Peruano - Pima Americano",
      "TMATEPRIM": "B",
      "TDESCMATEPRIM": "Algodon Tanguis",
      "TNUMEPIEZ": 4264911,
      "TSECUPIEZ": 0,
      "TFECHTEJE": "2025-12-13 14:25:00",
      "TCALIPIEZ": 1,
      "TDESCCALI": "1a Calidad",
      "TKILOPIEZ": 32.3,
      "TMETRPIEZ": 99.299,
      "TCODIMAQU": "0C0L5",
      "TNOMBMAQU": "Jersera L5 D30 96a",
      "TMODEMAQU": "S296-1",
      "TFABRMAQU": "Terrot",
      "TRPMSTND": 28.0,
      "TCODIPERS": "E003137",
      "TNOMBPERS": "John Cruz"
    },
    {
      "TORDETEJE": 1091773,
      "TTELAPRIN": "1",
      "TKILOCRUD": 199.62,
      "TNUMEOB": 4366898,
      "TREDUCRUD": 815353,
      "TCODITELA": "96213",
      "TDESCTELA": "Jersey solido 24/1upland souple c/ant msuave",
      "TNUMEGALG": 28,
      "TDESCTIPOARTI": "Tela",
      "THILOCOLO": "0",
      "TTIPOTEJI": "J",
      "TDESCTIPOTEJI": "Jersey",
      "TTIPOMAQUTEJE": "T",
      "TDESCTIPOMAQUTEJE": "Circular",
      "TCODIMATEPRIM": "E",
      "TDESCCODIMATEPRIM": "Mezcla Pima Peruano - Pima Americano",
      "TMATEPRIM": "B",
      "TDESCMATEPRIM": "Algodon Tanguis",
      "TNUMEPIEZ": 4264910,
      "TSECUPIEZ": 0,
      "TFECHTEJE": "2025-12-13 12:49:00",
      "TCALIPIEZ": 1,
      "TDESCCALI": "1a Calidad",
      "TKILOPIEZ": 32.5,
      "TMETRPIEZ": 99.914,
      "TCODIMAQU": "0C0L5",
      "TNOMBMAQU": "Jersera L5 D30 96a",
      "TMODEMAQU": "S296-1",
      "TFABRMAQU": "Terrot",
      "TRPMSTND": 28.0,
      "TCODIPERS": "E003137",
      "TNOMBPERS": "John Cruz"
    },
    {
      "TORDETEJE": 1091773,
      "TTELAPRIN": "1",
      "TKILOCRUD": 199.62,
      "TNUMEOB": 4366898,
      "TREDUCRUD": 815353,
      "TCODITELA": "96213",
      "TDESCTELA": "Jersey solido 24/1upland souple c/ant msuave",
      "TNUMEGALG": 28,
      "TDESCTIPOARTI": "Tela",
      "THILOCOLO": "0",
      "TTIPOTEJI": "J",
      "TDESCTIPOTEJI": "Jersey",
      "TTIPOMAQUTEJE": "T",
      "TDESCTIPOMAQUTEJE": "Circular",
      "TCODIMATEPRIM": "E",
      "TDESCCODIMATEPRIM": "Mezcla Pima Peruano - Pima Americano",
      "TMATEPRIM": "B",
      "TDESCMATEPRIM": "Algodon Tanguis",
      "TNUMEPIEZ": 4264914,
      "TSECUPIEZ": 0,
      "TFECHTEJE": "2025-12-13 20:33:00",
      "TCALIPIEZ": 1,
      "TDESCCALI": "1a Calidad",
      "TKILOPIEZ": 32.4,
      "TMETRPIEZ": 99.606,
      "TCODIMAQU": "0C0L5",
      "TNOMBMAQU": "Jersera L5 D30 96a",
      "TMODEMAQU": "S296-1",
      "TFABRMAQU": "Terrot",
      "TRPMSTND": 28.0,
      "TCODIPERS": "E002292",
      "TNOMBPERS": "Nilo De La Cruz"
    },
    {
      "TORDETEJE": 1091773,
      "TTELAPRIN": "1",
      "TKILOCRUD": 199.62,
      "TNUMEOB": 4366898,
      "TREDUCRUD": 815353,
      "TCODITELA": "96213",
      "TDESCTELA": "Jersey solido 24/1upland souple c/ant msuave",
      "TNUMEGALG": 28,
      "TDESCTIPOARTI": "Tela",
      "THILOCOLO": "0",
      "TTIPOTEJI": "J",
      "TDESCTIPOTEJI": "Jersey",
      "TTIPOMAQUTEJE": "T",
      "TDESCTIPOMAQUTEJE": "Circular",
      "TCODIMATEPRIM": "E",
      "TDESCCODIMATEPRIM": "Mezcla Pima Peruano - Pima Americano",
      "TMATEPRIM": "B",
      "TDESCMATEPRIM": "Algodon Tanguis",
      "TNUMEPIEZ": 4264915,
      "TSECUPIEZ": 1,
      "TFECHTEJE": "2025-12-13 23:54:00",
      "TCALIPIEZ": 1,
      "TDESCCALI": "1a Calidad",
      "TKILOPIEZ": 18.518,
      "TMETRPIEZ": 57.944,
      "TCODIMAQU": "0C0L5",
      "TNOMBMAQU": "Jersera L5 D30 96a",
      "TMODEMAQU": "S296-1",
      "TFABRMAQU": "Terrot",
      "TRPMSTND": 28.0,
      "TCODIPERS": "E002292",
      "TNOMBPERS": "Nilo De La Cruz"
    },
    {
      "TORDETEJE": 1091773,
      "TTELAPRIN": "1",
      "TKILOCRUD": 199.62,
      "TNUMEOB": 4366898,
      "TREDUCRUD": 815353,
      "TCODITELA": "96213",
      "TDESCTELA": "Jersey solido 24/1upland souple c/ant msuave",
      "TNUMEGALG": 28,
      "TDESCTIPOARTI": "Tela",
      "THILOCOLO": "0",
      "TTIPOTEJI": "J",
      "TDESCTIPOTEJI": "Jersey",
      "TTIPOMAQUTEJE": "T",
      "TDESCTIPOMAQUTEJE": "Circular",
      "TCODIMATEPRIM": "E",
      "TDESCCODIMATEPRIM": "Mezcla Pima Peruano - Pima Americano",
      "TMATEPRIM": "B",
      "TDESCMATEPRIM": "Algodon Tanguis",
      "TNUMEPIEZ": 4264909,
      "TSECUPIEZ": 0,
      "TFECHTEJE": "2025-12-13 11:11:00",
      "TCALIPIEZ": 1,
      "TDESCCALI": "1a Calidad",
      "TKILOPIEZ": 19.202,
      "TMETRPIEZ": 59.186,
      "TCODIMAQU": "0C0L5",
      "TNOMBMAQU": "Jersera L5 D30 96a",
      "TMODEMAQU": "S296-1",
      "TFABRMAQU": "Terrot",
      "TRPMSTND": 28.0,
      "TCODIPERS": "E003137",
      "TNOMBPERS": "John Cruz"
    },
    {
      "TORDETEJE": 1091773,
      "TTELAPRIN": "1",
      "TKILOCRUD": 199.62,
      "TNUMEOB": 4366898,
      "TREDUCRUD": 815353,
      "TCODITELA": "96213",
      "TDESCTELA": "Jersey solido 24/1upland souple c/ant msuave",
      "TNUMEGALG": 28,
      "TDESCTIPOARTI": "Tela",
      "THILOCOLO": "0",
      "TTIPOTEJI": "J",
      "TDESCTIPOTEJI": "Jersey",
      "TTIPOMAQUTEJE": "T",
      "TDESCTIPOMAQUTEJE": "Circular",
      "TCODIMATEPRIM": "E",
      "TDESCCODIMATEPRIM": "Mezcla Pima Peruano - Pima Americano",
      "TMATEPRIM": "B",
      "TDESCMATEPRIM": "Algodon Tanguis",
      "TNUMEPIEZ": 4264912,
      "TSECUPIEZ": 0,
      "TFECHTEJE": "2025-12-13 16:07:00",
      "TCALIPIEZ": 1,
      "TDESCCALI": "1a Calidad",
      "TKILOPIEZ": 32.3,
      "TMETRPIEZ": 99.299,
      "TCODIMAQU": "0C0L5",
      "TNOMBMAQU": "Jersera L5 D30 96a",
      "TMODEMAQU": "S296-1",
      "TFABRMAQU": "Terrot",
      "TRPMSTND": 28.0,
      "TCODIPERS": "E003137",
      "TNOMBPERS": "John Cruz"
    },
    {
      "TORDETEJE": 1092339,
      "TTELAPRIN": "0",
      "TNUMEOB": 4366904,
      "TREDUCRUD": 1192614,
      "TCODITELA": "5912K",
      "TDESCTELA": "Pu-ce-g12-c3-c241p0-l140a0-2-lm90-32 7/8 - 1 3/16",
      "TNUMEGALG": 12,
      "TDESCTIPOARTI": "Puño",
      "THILOCOLO": "0",
      "TTIPOTEJI": "C",
      "TDESCTIPOTEJI": "Rectilineos",
      "TTIPOMAQUTEJE": "N",
      "TDESCTIPOMAQUTEJE": "Rectilineos",
      "TCODIMATEPRIM": "L",
      "TDESCCODIMATEPRIM": "Lycra",
      "TMATEPRIM": "B",
      "TDESCMATEPRIM": "Algodon Tanguis",
      "TNUMEPIEZ": 4263845,
      "TSECUPIEZ": 1,
      "TFECHTEJE": "2025-12-09 13:37:00",
      "TCALIPIEZ": 1,
      "TDESCCALI": "1a Calidad",
      "TKILOPIEZ": 1.283,
      "TMETRPIEZ": 0.579,
      "TCODIMAQU": "0RA12",
      "TNOMBMAQU": "Protti A12 G12 F86",
      "TMODEMAQU": "Pt22j",
      "TFABRMAQU": "Protti",
      "TRPMSTND": 36.8796837198324,
      "TCODIPERS": "E003015",
      "TNOMBPERS": "Vicente Chavez"
    },
    {
      "TORDETEJE": 1090239,
      "TTELAPRIN": "0",
      "TNUMEOB": 4366904,
      "TREDUCRUD": 1192614,
      "TCODITELA": "5912K",
      "TDESCTELA": "Pu-ce-g12-c3-c241p0-l140a0-2-lm90-32 7/8 - 1 3/16",
      "TNUMEGALG": 12,
      "TDESCTIPOARTI": "Puño",
      "THILOCOLO": "0",
      "TTIPOTEJI": "C",
      "TDESCTIPOTEJI": "Rectilineos",
      "TTIPOMAQUTEJE": "N",
      "TDESCTIPOMAQUTEJE": "Rectilineos",
      "TCODIMATEPRIM": "L",
      "TDESCCODIMATEPRIM": "Lycra",
      "TMATEPRIM": "B",
      "TDESCMATEPRIM": "Algodon Tanguis",
      "TNUMEPIEZ": 4255977,
      "TSECUPIEZ": 0,
      "TFECHTEJE": "2025-11-04 21:34:00",
      "TCALIPIEZ": 1,
      "TDESCCALI": "1a Calidad",
      "TKILOPIEZ": 1.6,
      "TMETRPIEZ": 0.7,
      "TCODIMAQU": "0R076",
      "TNOMBMAQU": "Matsuya 76 G14 F40",
      "TMODEMAQU": "Matsuya",
      "TFABRMAQU": "Matsuya",
      "TRPMSTND": 36.8796837198324,
      "TCODIPERS": "E00D232",
      "TNOMBPERS": "Victor Huaman"
    },
    {
      "TORDETEJE": 1082782,
      "TTELAPRIN": "0",
      "TNUMEOB": 4366904,
      "TREDUCRUD": 1192614,
      "TCODITELA": "5912K",
      "TDESCTELA": "Pu-ce-g12-c3-c241p0-l140a0-2-lm90-32 7/8 - 1 3/16",
      "TNUMEGALG": 12,
      "TDESCTIPOARTI": "Puño",
      "THILOCOLO": "0",
      "TTIPOTEJI": "C",
      "TDESCTIPOTEJI": "Rectilineos",
      "TTIPOMAQUTEJE": "N",
      "TDESCTIPOMAQUTEJE": "Rectilineos",
      "TCODIMATEPRIM": "L",
      "TDESCCODIMATEPRIM": "Lycra",
      "TMATEPRIM": "B",
      "TDESCMATEPRIM": "Algodon Tanguis",
      "TNUMEPIEZ": 4229024,
      "TSECUPIEZ": 0,
      "TFECHTEJE": "2025-08-27 03:13:00",
      "TCALIPIEZ": 1,
      "TDESCCALI": "1a Calidad",
      "TKILOPIEZ": 0.536,
      "TMETRPIEZ": 0.223,
      "TCODIMAQU": "0R014",
      "TNOMBMAQU": "Matsuya 14 G16 F40",
      "TMODEMAQU": "Matsuya",
      "TFABRMAQU": "Matsuya",
      "TRPMSTND": 36.8796837198324,
      "TCODIPERS": "E00D232",
      "TNOMBPERS": "Victor Huaman"
    },
    {
      "TORDETEJE": 1082781,
      "TTELAPRIN": "0",
      "TNUMEOB": 4366905,
      "TREDUCRUD": 1194401,
      "TCODITELA": "5912K",
      "TDESCTELA": "Pu-ce-g12-c3-c241p0-l140a0-2-lm90-32 7/8 - 1 3/16",
      "TNUMEGALG": 12,
      "TDESCTIPOARTI": "Puño",
      "THILOCOLO": "0",
      "TTIPOTEJI": "C",
      "TDESCTIPOTEJI": "Rectilineos",
      "TTIPOMAQUTEJE": "N",
      "TDESCTIPOMAQUTEJE": "Rectilineos",
      "TCODIMATEPRIM": "L",
      "TDESCCODIMATEPRIM": "Lycra",
      "TMATEPRIM": "B",
      "TDESCMATEPRIM": "Algodon Tanguis",
      "TNUMEPIEZ": 4228983,
      "TSECUPIEZ": 0,
      "TFECHTEJE": "2025-08-27 03:13:00",
      "TCALIPIEZ": 1,
      "TDESCCALI": "1a Calidad",
      "TKILOPIEZ": 1.507,
      "TMETRPIEZ": 0.603,
      "TCODIMAQU": "0R014",
      "TNOMBMAQU": "Matsuya 14 G16 F40",
      "TMODEMAQU": "Matsuya",
      "TFABRMAQU": "Matsuya",
      "TRPMSTND": 36.8796837198324,
      "TCODIPERS": "E00D232",
      "TNOMBPERS": "Victor Huaman"
    },
    {
      "TORDETEJE": 1082626,
      "TTELAPRIN": "0",
      "TNUMEOB": 4366905,
      "TREDUCRUD": 1194401,
      "TCODITELA": "5912K",
      "TDESCTELA": "Pu-ce-g12-c3-c241p0-l140a0-2-lm90-32 7/8 - 1 3/16",
      "TNUMEGALG": 12,
      "TDESCTIPOARTI": "Puño",
      "THILOCOLO": "0",
      "TTIPOTEJI": "C",
      "TDESCTIPOTEJI": "Rectilineos",
      "TTIPOMAQUTEJE": "N",
      "TDESCTIPOMAQUTEJE": "Rectilineos",
      "TCODIMATEPRIM": "L",
      "TDESCCODIMATEPRIM": "Lycra",
      "TMATEPRIM": "B",
      "TDESCMATEPRIM": "Algodon Tanguis",
      "TNUMEPIEZ": 4228624,
      "TSECUPIEZ": 0,
      "TFECHTEJE": "2025-08-23 01:08:00",
      "TCALIPIEZ": 1,
      "TDESCCALI": "1a Calidad",
      "TKILOPIEZ": 2.35,
      "TMETRPIEZ": 0.839,
      "TCODIMAQU": "0R021",
      "TNOMBMAQU": "Matsuya 21 G16 F40",
      "TMODEMAQU": "Matsuya",
      "TFABRMAQU": "Matsuya",
      "TRPMSTND": 36.8796837198324,
      "TCODIPERS": "E004595",
      "TNOMBPERS": "Jose Mozombite"
    },
    {
      "TORDETEJE": 1082625,
      "TTELAPRIN": "0",
      "TNUMEOB": 4366906,
      "TREDUCRUD": 1194402,
      "TCODITELA": "5912K",
      "TDESCTELA": "Pu-ce-g12-c3-c241p0-l140a0-2-lm90-32 7/8 - 1 3/16",
      "TNUMEGALG": 12,
      "TDESCTIPOARTI": "Puño",
      "THILOCOLO": "0",
      "TTIPOTEJI": "C",
      "TDESCTIPOTEJI": "Rectilineos",
      "TTIPOMAQUTEJE": "N",
      "TDESCTIPOMAQUTEJE": "Rectilineos",
      "TCODIMATEPRIM": "L",
      "TDESCCODIMATEPRIM": "Lycra",
      "TMATEPRIM": "B",
      "TDESCMATEPRIM": "Algodon Tanguis",
      "TNUMEPIEZ": 4228623,
      "TSECUPIEZ": 1,
      "TFECHTEJE": "2025-08-23 01:08:00",
      "TCALIPIEZ": 1,
      "TDESCCALI": "1a Calidad",
      "TKILOPIEZ": 1.411,
      "TMETRPIEZ": 0.483,
      "TCODIMAQU": "0R021",
      "TNOMBMAQU": "Matsuya 21 G16 F40",
      "TMODEMAQU": "Matsuya",
      "TFABRMAQU": "Matsuya",
      "TRPMSTND": 36.8796837198324,
      "TCODIPERS": "E004595",
      "TNOMBPERS": "Jose Mozombite"
    },
    {
      "TORDETEJE": 1082780,
      "TTELAPRIN": "0",
      "TNUMEOB": 4366906,
      "TREDUCRUD": 1194402,
      "TCODITELA": "5912K",
      "TDESCTELA": "Pu-ce-g12-c3-c241p0-l140a0-2-lm90-32 7/8 - 1 3/16",
      "TNUMEGALG": 12,
      "TDESCTIPOARTI": "Puño",
      "THILOCOLO": "0",
      "TTIPOTEJI": "C",
      "TDESCTIPOTEJI": "Rectilineos",
      "TTIPOMAQUTEJE": "N",
      "TDESCTIPOMAQUTEJE": "Rectilineos",
      "TCODIMATEPRIM": "L",
      "TDESCCODIMATEPRIM": "Lycra",
      "TMATEPRIM": "B",
      "TDESCMATEPRIM": "Algodon Tanguis",
      "TNUMEPIEZ": 4229023,
      "TSECUPIEZ": 0,
      "TFECHTEJE": "2025-08-27 03:13:00",
      "TCALIPIEZ": 1,
      "TDESCCALI": "1a Calidad",
      "TKILOPIEZ": 1.72,
      "TMETRPIEZ": 0.664,
      "TCODIMAQU": "0R014",
      "TNOMBMAQU": "Matsuya 14 G16 F40",
      "TMODEMAQU": "Matsuya",
      "TFABRMAQU": "Matsuya",
      "TRPMSTND": 36.8796837198324,
      "TCODIPERS": "E00D232",
      "TNOMBPERS": "Victor Huaman"
    },
    {
      "TORDETEJE": 1082783,
      "TTELAPRIN": "0",
      "TNUMEOB": 4366907,
      "TREDUCRUD": 1194400,
      "TCODITELA": "5912K",
      "TDESCTELA": "Pu-ce-g12-c3-c241p0-l140a0-2-lm90-32 7/8 - 1 3/16",
      "TNUMEGALG": 12,
      "TDESCTIPOARTI": "Puño",
      "THILOCOLO": "0",
      "TTIPOTEJI": "C",
      "TDESCTIPOTEJI": "Rectilineos",
      "TTIPOMAQUTEJE": "N",
      "TDESCTIPOMAQUTEJE": "Rectilineos",
      "TCODIMATEPRIM": "L",
      "TDESCCODIMATEPRIM": "Lycra",
      "TMATEPRIM": "B",
      "TDESCMATEPRIM": "Algodon Tanguis",
      "TNUMEPIEZ": 4229025,
      "TSECUPIEZ": 0,
      "TFECHTEJE": "2025-08-27 03:13:00",
      "TCALIPIEZ": 1,
      "TDESCCALI": "1a Calidad",
      "TKILOPIEZ": 0.661,
      "TMETRPIEZ": 0.29,
      "TCODIMAQU": "0R014",
      "TNOMBMAQU": "Matsuya 14 G16 F40",
      "TMODEMAQU": "Matsuya",
      "TFABRMAQU": "Matsuya",
      "TRPMSTND": 36.8796837198324,
      "TCODIPERS": "E00D232",
      "TNOMBPERS": "Victor Huaman"
    },
    {
      "TORDETEJE": 1082628,
      "TTELAPRIN": "0",
      "TNUMEOB": 4366907,
      "TREDUCRUD": 1194400,
      "TCODITELA": "5912K",
      "TDESCTELA": "Pu-ce-g12-c3-c241p0-l140a0-2-lm90-32 7/8 - 1 3/16",
      "TNUMEGALG": 12,
      "TDESCTIPOARTI": "Puño",
      "THILOCOLO": "0",
      "TTIPOTEJI": "C",
      "TDESCTIPOTEJI": "Rectilineos",
      "TTIPOMAQUTEJE": "N",
      "TDESCTIPOMAQUTEJE": "Rectilineos",
      "TCODIMATEPRIM": "L",
      "TDESCCODIMATEPRIM": "Lycra",
      "TMATEPRIM": "B",
      "TDESCMATEPRIM": "Algodon Tanguis",
      "TNUMEPIEZ": 4228626,
      "TSECUPIEZ": 0,
      "TFECHTEJE": "2025-08-23 01:08:00",
      "TCALIPIEZ": 1,
      "TDESCCALI": "1a Calidad",
      "TKILOPIEZ": 1.07,
      "TMETRPIEZ": 0.416,
      "TCODIMAQU": "0R021",
      "TNOMBMAQU": "Matsuya 21 G16 F40",
      "TMODEMAQU": "Matsuya",
      "TFABRMAQU": "Matsuya",
      "TRPMSTND": 36.8796837198324,
      "TCODIPERS": "E004595",
      "TNOMBPERS": "Jose Mozombite"
    },
    {
      "TORDETEJE": 1082624,
      "TTELAPRIN": "0",
      "TNUMEOB": 4366908,
      "TREDUCRUD": 1194403,
      "TCODITELA": "5912K",
      "TDESCTELA": "Pu-ce-g12-c3-c241p0-l140a0-2-lm90-32 7/8 - 1 3/16",
      "TNUMEGALG": 12,
      "TDESCTIPOARTI": "Puño",
      "THILOCOLO": "0",
      "TTIPOTEJI": "C",
      "TDESCTIPOTEJI": "Rectilineos",
      "TTIPOMAQUTEJE": "N",
      "TDESCTIPOMAQUTEJE": "Rectilineos",
      "TCODIMATEPRIM": "L",
      "TDESCCODIMATEPRIM": "Lycra",
      "TMATEPRIM": "B",
      "TDESCMATEPRIM": "Algodon Tanguis",
      "TNUMEPIEZ": 4228622,
      "TSECUPIEZ": 1,
      "TFECHTEJE": "2025-08-23 01:08:00",
      "TCALIPIEZ": 1,
      "TDESCCALI": "1a Calidad",
      "TKILOPIEZ": 0.446,
      "TMETRPIEZ": 0.145,
      "TCODIMAQU": "0R021",
      "TNOMBMAQU": "Matsuya 21 G16 F40",
      "TMODEMAQU": "Matsuya",
      "TFABRMAQU": "Matsuya",
      "TRPMSTND": 36.8796837198324,
      "TCODIPERS": "E004595",
      "TNOMBPERS": "Jose Mozombite"
    },
    {
      "TORDETEJE": 1082779,
      "TTELAPRIN": "0",
      "TNUMEOB": 4366908,
      "TREDUCRUD": 1194403,
      "TCODITELA": "5912K",
      "TDESCTELA": "Pu-ce-g12-c3-c241p0-l140a0-2-lm90-32 7/8 - 1 3/16",
      "TNUMEGALG": 12,
      "TDESCTIPOARTI": "Puño",
      "THILOCOLO": "0",
      "TTIPOTEJI": "C",
      "TDESCTIPOTEJI": "Rectilineos",
      "TTIPOMAQUTEJE": "N",
      "TDESCTIPOMAQUTEJE": "Rectilineos",
      "TCODIMATEPRIM": "L",
      "TDESCCODIMATEPRIM": "Lycra",
      "TMATEPRIM": "B",
      "TDESCMATEPRIM": "Algodon Tanguis",
      "TNUMEPIEZ": 4229022,
      "TSECUPIEZ": 0,
      "TFECHTEJE": "2025-08-27 03:13:00",
      "TCALIPIEZ": 1,
      "TDESCCALI": "1a Calidad",
      "TKILOPIEZ": 1.03,
      "TMETRPIEZ": 0.38,
      "TCODIMAQU": "0R014",
      "TNOMBMAQU": "Matsuya 14 G16 F40",
      "TMODEMAQU": "Matsuya",
      "TFABRMAQU": "Matsuya",
      "TRPMSTND": 36.8796837198324,
      "TCODIPERS": "E00D232",
      "TNOMBPERS": "Victor Huaman"
    },
    {
      "TORDETEJE": 1082623,
      "TTELAPRIN": "0",
      "TNUMEOB": 4366909,
      "TREDUCRUD": 1194404,
      "TCODITELA": "5912K",
      "TDESCTELA": "Pu-ce-g12-c3-c241p0-l140a0-2-lm90-32 7/8 - 1 3/16",
      "TNUMEGALG": 12,
      "TDESCTIPOARTI": "Puño",
      "THILOCOLO": "0",
      "TTIPOTEJI": "C",
      "TDESCTIPOTEJI": "Rectilineos",
      "TTIPOMAQUTEJE": "N",
      "TDESCTIPOMAQUTEJE": "Rectilineos",
      "TCODIMATEPRIM": "L",
      "TDESCCODIMATEPRIM": "Lycra",
      "TMATEPRIM": "B",
      "TDESCMATEPRIM": "Algodon Tanguis",
      "TNUMEPIEZ": 4228621,
      "TSECUPIEZ": 1,
      "TFECHTEJE": "2025-08-23 01:08:00",
      "TCALIPIEZ": 1,
      "TDESCCALI": "1a Calidad",
      "TKILOPIEZ": 0.288,
      "TMETRPIEZ": 0.09,
      "TCODIMAQU": "0R021",
      "TNOMBMAQU": "Matsuya 21 G16 F40",
      "TMODEMAQU": "Matsuya",
      "TFABRMAQU": "Matsuya",
      "TRPMSTND": 36.8796837198324,
      "TCODIPERS": "E004595",
      "TNOMBPERS": "Jose Mozombite"
    },
    {
      "TORDETEJE": 1082770,
      "TTELAPRIN": "0",
      "TNUMEOB": 4366909,
      "TREDUCRUD": 1194404,
      "TCODITELA": "5912K",
      "TDESCTELA": "Pu-ce-g12-c3-c241p0-l140a0-2-lm90-32 7/8 - 1 3/16",
      "TNUMEGALG": 12,
      "TDESCTIPOARTI": "Puño",
      "THILOCOLO": "0",
      "TTIPOTEJI": "C",
      "TDESCTIPOTEJI": "Rectilineos",
      "TTIPOMAQUTEJE": "N",
      "TDESCTIPOMAQUTEJE": "Rectilineos",
      "TCODIMATEPRIM": "L",
      "TDESCCODIMATEPRIM": "Lycra",
      "TMATEPRIM": "B",
      "TDESCMATEPRIM": "Algodon Tanguis",
      "TNUMEPIEZ": 4229013,
      "TSECUPIEZ": 0,
      "TFECHTEJE": "2025-08-25 19:41:00",
      "TCALIPIEZ": 1,
      "TDESCCALI": "1a Calidad",
      "TKILOPIEZ": 0.208,
      "TMETRPIEZ": 0.072,
      "TCODIMAQU": "0R014",
      "TNOMBMAQU": "Matsuya 14 G16 F40",
      "TMODEMAQU": "Matsuya",
      "TFABRMAQU": "Matsuya",
      "TRPMSTND": 36.8796837198324,
      "TCODIPERS": "E004595",
      "TNOMBPERS": "Jose Mozombite"
    },
    {
      "TORDETEJE": 1082778,
      "TTELAPRIN": "0",
      "TNUMEOB": 4366909,
      "TREDUCRUD": 1194404,
      "TCODITELA": "5912K",
      "TDESCTELA": "Pu-ce-g12-c3-c241p0-l140a0-2-lm90-32 7/8 - 1 3/16",
      "TNUMEGALG": 12,
      "TDESCTIPOARTI": "Puño",
      "THILOCOLO": "0",
      "TTIPOTEJI": "C",
      "TDESCTIPOTEJI": "Rectilineos",
      "TTIPOMAQUTEJE": "N",
      "TDESCTIPOMAQUTEJE": "Rectilineos",
      "TCODIMATEPRIM": "L",
      "TDESCCODIMATEPRIM": "Lycra",
      "TMATEPRIM": "B",
      "TDESCMATEPRIM": "Algodon Tanguis",
      "TNUMEPIEZ": 4229021,
      "TSECUPIEZ": 0,
      "TFECHTEJE": "2025-08-27 03:13:00",
      "TCALIPIEZ": 1,
      "TDESCCALI": "1a Calidad",
      "TKILOPIEZ": 0.89,
      "TMETRPIEZ": 0.314,
      "TCODIMAQU": "0R014",
      "TNOMBMAQU": "Matsuya 14 G16 F40",
      "TMODEMAQU": "Matsuya",
      "TFABRMAQU": "Matsuya",
      "TRPMSTND": 36.8796837198324,
      "TCODIPERS": "E00D232",
      "TNOMBPERS": "Victor Huaman"
    },
    {
      "TORDETEJE": 1090237,
      "TTELAPRIN": "0",
      "TNUMEOB": 4366910,
      "TREDUCRUD": 1194405,
      "TCODITELA": "5912K",
      "TDESCTELA": "Pu-ce-g12-c3-c241p0-l140a0-2-lm90-32 7/8 - 1 3/16",
      "TNUMEGALG": 12,
      "TDESCTIPOARTI": "Puño",
      "THILOCOLO": "0",
      "TTIPOTEJI": "C",
      "TDESCTIPOTEJI": "Rectilineos",
      "TTIPOMAQUTEJE": "N",
      "TDESCTIPOMAQUTEJE": "Rectilineos",
      "TCODIMATEPRIM": "L",
      "TDESCCODIMATEPRIM": "Lycra",
      "TMATEPRIM": "B",
      "TDESCMATEPRIM": "Algodon Tanguis",
      "TNUMEPIEZ": 4255975,
      "TSECUPIEZ": 0,
      "TFECHTEJE": "2025-11-04 04:28:00",
      "TCALIPIEZ": 1,
      "TDESCCALI": "1a Calidad",
      "TKILOPIEZ": 0.292,
      "TMETRPIEZ": 0.09,
      "TCODIMAQU": "0R076",
      "TNOMBMAQU": "Matsuya 76 G14 F40",
      "TMODEMAQU": "Matsuya",
      "TFABRMAQU": "Matsuya",
      "TRPMSTND": 36.8796837198324,
      "TCODIPERS": "E004557",
      "TNOMBPERS": "Alwin Lachuma"
    },
    {
      "TORDETEJE": 1082622,
      "TTELAPRIN": "0",
      "TNUMEOB": 4366910,
      "TREDUCRUD": 1194405,
      "TCODITELA": "5912K",
      "TDESCTELA": "Pu-ce-g12-c3-c241p0-l140a0-2-lm90-32 7/8 - 1 3/16",
      "TNUMEGALG": 12,
      "TDESCTIPOARTI": "Puño",
      "THILOCOLO": "0",
      "TTIPOTEJI": "C",
      "TDESCTIPOTEJI": "Rectilineos",
      "TTIPOMAQUTEJE": "N",
      "TDESCTIPOMAQUTEJE": "Rectilineos",
      "TCODIMATEPRIM": "L",
      "TDESCCODIMATEPRIM": "Lycra",
      "TMATEPRIM": "B",
      "TDESCMATEPRIM": "Algodon Tanguis",
      "TNUMEPIEZ": 4228620,
      "TSECUPIEZ": 0,
      "TFECHTEJE": "2025-08-23 01:08:00",
      "TCALIPIEZ": 1,
      "TDESCCALI": "1a Calidad",
      "TKILOPIEZ": 0.49,
      "TMETRPIEZ": 0.145,
      "TCODIMAQU": "0R021",
      "TNOMBMAQU": "Matsuya 21 G16 F40",
      "TMODEMAQU": "Matsuya",
      "TFABRMAQU": "Matsuya",
      "TRPMSTND": 36.8796837198324,
      "TCODIPERS": "E004595",
      "TNOMBPERS": "Jose Mozombite"
    },
    {
      "TORDETEJE": 1082777,
      "TTELAPRIN": "0",
      "TNUMEOB": 4366910,
      "TREDUCRUD": 1194405,
      "TCODITELA": "5912K",
      "TDESCTELA": "Pu-ce-g12-c3-c241p0-l140a0-2-lm90-32 7/8 - 1 3/16",
      "TNUMEGALG": 12,
      "TDESCTIPOARTI": "Puño",
      "THILOCOLO": "0",
      "TTIPOTEJI": "C",
      "TDESCTIPOTEJI": "Rectilineos",
      "TTIPOMAQUTEJE": "N",
      "TDESCTIPOMAQUTEJE": "Rectilineos",
      "TCODIMATEPRIM": "L",
      "TDESCCODIMATEPRIM": "Lycra",
      "TMATEPRIM": "B",
      "TDESCMATEPRIM": "Algodon Tanguis",
      "TNUMEPIEZ": 4229020,
      "TSECUPIEZ": 0,
      "TFECHTEJE": "2025-08-27 03:13:00",
      "TCALIPIEZ": 1,
      "TDESCCALI": "1a Calidad",
      "TKILOPIEZ": 0.22,
      "TMETRPIEZ": 0.073,
      "TCODIMAQU": "0R014",
      "TNOMBMAQU": "Matsuya 14 G16 F40",
      "TMODEMAQU": "Matsuya",
      "TFABRMAQU": "Matsuya",
      "TRPMSTND": 36.8796837198324,
      "TCODIPERS": "E00D232",
      "TNOMBPERS": "Victor Huaman"
    },
    {
      "TORDETEJE": 1090240,
      "TTELAPRIN": "0",
      "TNUMEOB": 4366911,
      "TREDUCRUD": 1194399,
      "TCODITELA": "5912K",
      "TDESCTELA": "Pu-ce-g12-c3-c241p0-l140a0-2-lm90-32 7/8 - 1 3/16",
      "TNUMEGALG": 12,
      "TDESCTIPOARTI": "Puño",
      "THILOCOLO": "0",
      "TTIPOTEJI": "C",
      "TDESCTIPOTEJI": "Rectilineos",
      "TTIPOMAQUTEJE": "N",
      "TDESCTIPOMAQUTEJE": "Rectilineos",
      "TCODIMATEPRIM": "L",
      "TDESCCODIMATEPRIM": "Lycra",
      "TMATEPRIM": "B",
      "TDESCMATEPRIM": "Algodon Tanguis",
      "TNUMEPIEZ": 4255978,
      "TSECUPIEZ": 0,
      "TFECHTEJE": "2025-11-05 01:08:00",
      "TCALIPIEZ": 1,
      "TDESCCALI": "1a Calidad",
      "TKILOPIEZ": 0.3,
      "TMETRPIEZ": 0.133,
      "TCODIMAQU": "0R076",
      "TNOMBMAQU": "Matsuya 76 G14 F40",
      "TMODEMAQU": "Matsuya",
      "TFABRMAQU": "Matsuya",
      "TRPMSTND": 36.8796837198324,
      "TCODIPERS": "E004557",
      "TNOMBPERS": "Alwin Lachuma"
    },
    {
      "TORDETEJE": 1082629,
      "TTELAPRIN": "0",
      "TNUMEOB": 4366911,
      "TREDUCRUD": 1194399,
      "TCODITELA": "5912K",
      "TDESCTELA": "Pu-ce-g12-c3-c241p0-l140a0-2-lm90-32 7/8 - 1 3/16",
      "TNUMEGALG": 12,
      "TDESCTIPOARTI": "Puño",
      "THILOCOLO": "0",
      "TTIPOTEJI": "C",
      "TDESCTIPOTEJI": "Rectilineos",
      "TTIPOMAQUTEJE": "N",
      "TDESCTIPOMAQUTEJE": "Rectilineos",
      "TCODIMATEPRIM": "L",
      "TDESCCODIMATEPRIM": "Lycra",
      "TMATEPRIM": "B",
      "TDESCMATEPRIM": "Algodon Tanguis",
      "TNUMEPIEZ": 4228599,
      "TSECUPIEZ": 0,
      "TFECHTEJE": "2025-08-23 01:08:00",
      "TCALIPIEZ": 1,
      "TDESCCALI": "1a Calidad",
      "TKILOPIEZ": 0.37,
      "TMETRPIEZ": 0.145,
      "TCODIMAQU": "0R021",
      "TNOMBMAQU": "Matsuya 21 G16 F40",
      "TMODEMAQU": "Matsuya",
      "TFABRMAQU": "Matsuya",
      "TRPMSTND": 36.8796837198324,
      "TCODIPERS": "E004595",
      "TNOMBPERS": "Jose Mozombite"
    }
  ],
  "tztotrazwebhilo": [
    {
      "TREDUCRUD": 1194401,
      "TTELAPRIN": "0",
      "TCODITELA": "5912K",
      "TDESCTELA": "Pu-ce-g12-c3-c241p0-l140a0-2-lm90-32 7/8 - 1 3/16",
      "TDESCTIPOARTI": "Puño",
      "TLOTEHILA": "AU05F7",
      "TLOTENETT": "AU05F7-23"
    },
    {
      "TREDUCRUD": 1194402,
      "TTELAPRIN": "0",
      "TCODITELA": "5912K",
      "TDESCTELA": "Pu-ce-g12-c3-c241p0-l140a0-2-lm90-32 7/8 - 1 3/16",
      "TDESCTIPOARTI": "Puño",
      "TLOTEHILA": "AU05F7",
      "TLOTENETT": "AU05F7-23"
    },
    {
      "TREDUCRUD": 1194405,
      "TTELAPRIN": "0",
      "TCODITELA": "5912K",
      "TDESCTELA": "Pu-ce-g12-c3-c241p0-l140a0-2-lm90-32 7/8 - 1 3/16",
      "TDESCTIPOARTI": "Puño",
      "TLOTEHILA": "AUC5G5",
      "TLOTENETT": "AUC5G5-37"
    },
    {
      "TREDUCRUD": 1092168,
      "TTELAPRIN": "0",
      "TCODITELA": "2741K",
      "TDESCTELA": "Cu-ce-g12-c3-c241p0-lm90-16 1/8 - 3 3/4",
      "TDESCTIPOARTI": "Cuello",
      "TLOTEHILA": "AU05F7",
      "TLOTENETT": "AU05F7-31"
    },
    {
      "TREDUCRUD": 1092167,
      "TTELAPRIN": "0",
      "TCODITELA": "2741K",
      "TDESCTELA": "Cu-ce-g12-c3-c241p0-lm90-16 1/8 - 3 3/4",
      "TDESCTIPOARTI": "Cuello",
      "TLOTEHILA": "AUC5G5",
      "TLOTENETT": "AUC5G5-37"
    },
    {
      "TREDUCRUD": 1092169,
      "TTELAPRIN": "0",
      "TCODITELA": "2741K",
      "TDESCTELA": "Cu-ce-g12-c3-c241p0-lm90-16 1/8 - 3 3/4",
      "TDESCTIPOARTI": "Cuello",
      "TLOTEHILA": "AUC5G5",
      "TLOTENETT": "AUC5G5-39"
    },
    {
      "TREDUCRUD": 1194399,
      "TTELAPRIN": "0",
      "TCODITELA": "5912K",
      "TDESCTELA": "Pu-ce-g12-c3-c241p0-l140a0-2-lm90-32 7/8 - 1 3/16",
      "TDESCTIPOARTI": "Puño",
      "TLOTEHILA": "AU05F7",
      "TLOTENETT": "AU05F7-23"
    },
    {
      "TREDUCRUD": 1092169,
      "TTELAPRIN": "0",
      "TCODITELA": "2741K",
      "TDESCTELA": "Cu-ce-g12-c3-c241p0-lm90-16 1/8 - 3 3/4",
      "TDESCTIPOARTI": "Cuello",
      "TLOTEHILA": "AUC5G5",
      "TLOTENETT": "AUC5G5-37"
    },
    {
      "TREDUCRUD": 815353,
      "TTELAPRIN": "1",
      "TCODITELA": "96213",
      "TDESCTELA": "Jersey solido 24/1upland souple c/ant msuave",
      "TDESCTIPOARTI": "Tela",
      "TREDUHILOPRIN": 15609.0,
      "THILOPRIN": "C241P",
      "TDESCHILOPRIN": "Alg. Upland 241 Peinado Parafinado",
      "TLOTEHILA": "AU05F7",
      "TLOTENETT": "AU05F7-43",
      "TPROVPRIN": "190136",
      "TNOMBPROVPRIN": "Filasur"
    },
    {
      "TREDUCRUD": 1194405,
      "TTELAPRIN": "0",
      "TCODITELA": "5912K",
      "TDESCTELA": "Pu-ce-g12-c3-c241p0-l140a0-2-lm90-32 7/8 - 1 3/16",
      "TDESCTIPOARTI": "Puño",
      "TLOTEHILA": "AU05F7",
      "TLOTENETT": "AU05F7-23"
    },
    {
      "TREDUCRUD": 1092167,
      "TTELAPRIN": "0",
      "TCODITELA": "2741K",
      "TDESCTELA": "Cu-ce-g12-c3-c241p0-lm90-16 1/8 - 3 3/4",
      "TDESCTIPOARTI": "Cuello",
      "TLOTEHILA": "AUC5G5",
      "TLOTENETT": "AUC5G5-39"
    },
    {
      "TREDUCRUD": 1194404,
      "TTELAPRIN": "0",
      "TCODITELA": "5912K",
      "TDESCTELA": "Pu-ce-g12-c3-c241p0-l140a0-2-lm90-32 7/8 - 1 3/16",
      "TDESCTIPOARTI": "Puño",
      "TLOTEHILA": "AU05F7",
      "TLOTENETT": "AU05F7-23"
    },
    {
      "TREDUCRUD": 1092168,
      "TTELAPRIN": "0",
      "TCODITELA": "2741K",
      "TDESCTELA": "Cu-ce-g12-c3-c241p0-lm90-16 1/8 - 3 3/4",
      "TDESCTIPOARTI": "Cuello",
      "TLOTEHILA": "AU05F7",
      "TLOTENETT": "AU05F7-23"
    },
    {
      "TREDUCRUD": 1092170,
      "TTELAPRIN": "0",
      "TCODITELA": "2741K",
      "TDESCTELA": "Cu-ce-g12-c3-c241p0-lm90-16 1/8 - 3 3/4",
      "TDESCTIPOARTI": "Cuello",
      "TLOTEHILA": "AUC5G5",
      "TLOTENETT": "AUC5G5-37"
    },
    {
      "TREDUCRUD": 1194399,
      "TTELAPRIN": "0",
      "TCODITELA": "5912K",
      "TDESCTELA": "Pu-ce-g12-c3-c241p0-l140a0-2-lm90-32 7/8 - 1 3/16",
      "TDESCTIPOARTI": "Puño",
      "TLOTEHILA": "AUC5G5",
      "TLOTENETT": "AUC5G5-37"
    },
    {
      "TREDUCRUD": 1072252,
      "TTELAPRIN": "0",
      "TCODITELA": "2741K",
      "TDESCTELA": "Cu-ce-g12-c3-c241p0-lm90-16 1/8 - 3 3/4",
      "TDESCTIPOARTI": "Cuello",
      "TLOTEHILA": "AUC5G5",
      "TLOTENETT": "AUC5G5-39"
    },
    {
      "TREDUCRUD": 1092168,
      "TTELAPRIN": "0",
      "TCODITELA": "2741K",
      "TDESCTELA": "Cu-ce-g12-c3-c241p0-lm90-16 1/8 - 3 3/4",
      "TDESCTIPOARTI": "Cuello",
      "TLOTEHILA": "AUC5G5",
      "TLOTENETT": "AUC5G5-37"
    },
    {
      "TREDUCRUD": 1192614,
      "TTELAPRIN": "0",
      "TCODITELA": "5912K",
      "TDESCTELA": "Pu-ce-g12-c3-c241p0-l140a0-2-lm90-32 7/8 - 1 3/16",
      "TDESCTIPOARTI": "Puño",
      "TLOTEHILA": "AUC5G5",
      "TLOTENETT": "AUC5G5-37"
    },
    {
      "TREDUCRUD": 1192614,
      "TTELAPRIN": "0",
      "TCODITELA": "5912K",
      "TDESCTELA": "Pu-ce-g12-c3-c241p0-l140a0-2-lm90-32 7/8 - 1 3/16",
      "TDESCTIPOARTI": "Puño",
      "TLOTEHILA": "AU05F7",
      "TLOTENETT": "AU05F7-23"
    },
    {
      "TREDUCRUD": 1194400,
      "TTELAPRIN": "0",
      "TCODITELA": "5912K",
      "TDESCTELA": "Pu-ce-g12-c3-c241p0-l140a0-2-lm90-32 7/8 - 1 3/16",
      "TDESCTIPOARTI": "Puño",
      "TLOTEHILA": "AU05F7",
      "TLOTENETT": "AU05F7-23"
    },
    {
      "TREDUCRUD": 1194403,
      "TTELAPRIN": "0",
      "TCODITELA": "5912K",
      "TDESCTELA": "Pu-ce-g12-c3-c241p0-l140a0-2-lm90-32 7/8 - 1 3/16",
      "TDESCTIPOARTI": "Puño",
      "TLOTEHILA": "AU05F7",
      "TLOTENETT": "AU05F7-23"
    },
    {
      "TREDUCRUD": 1072252,
      "TTELAPRIN": "0",
      "TCODITELA": "2741K",
      "TDESCTELA": "Cu-ce-g12-c3-c241p0-lm90-16 1/8 - 3 3/4",
      "TDESCTIPOARTI": "Cuello",
      "TLOTEHILA": "AU05F7",
      "TLOTENETT": "AU05F7-36"
    },
    {
      "TREDUCRUD": 1192614,
      "TTELAPRIN": "0",
      "TCODITELA": "5912K",
      "TDESCTELA": "Pu-ce-g12-c3-c241p0-l140a0-2-lm90-32 7/8 - 1 3/16",
      "TDESCTIPOARTI": "Puño",
      "TLOTEHILA": "AUC5G5",
      "TLOTENETT": "AUC5G5-39"
    }
  ],
  "tztotrazwebhiloloteprin": [
    {
      "TLOTENETT": "AUC5G5-37",
      "TGUIAHILO": "001-10897",
      "TFECHGUIAHILO": "2025-10-28 00:00:00",
      "TPESOGUIAHILO": 979.75,
      "TZONAORIGHILO": "Lima (Perú)",
      "TNUMEORDECOMP": 2025005489.0,
      "TFECHORDECOMP": "2025-05-21 00:00:00",
      "TNUMEFACTHILO": "FAC:F001-00047916 SOCAP"
    },
    {
      "TLOTENETT": "AUC5G5-37 ",
      "TGUIAHILO": "10637",
      "TFECHGUIAHILO": "NaT",
      "TFECHORDECOMP": "NaT"
    },
    {
      "TLOTENETT": "AUC5G5-39",
      "TGUIAHILO": "001-10909",
      "TFECHGUIAHILO": "2025-10-29 00:00:00",
      "TPESOGUIAHILO": 4224.75,
      "TZONAORIGHILO": "Lima (Perú)",
      "TNUMEORDECOMP": 2025005768.0,
      "TFECHORDECOMP": "2025-05-28 00:00:00",
      "TNUMEFACTHILO": "FAC:F001-00047936 SOCAP"
    },
    {
      "TLOTENETT": "AU05F7-23",
      "TGUIAHILO": "001-9127",
      "TFECHGUIAHILO": "2025-06-12 00:00:00",
      "TPESOGUIAHILO": 908.4,
      "TZONAORIGHILO": "Lima (Perú)",
      "TNUMEORDECOMP": 2025005485.0,
      "TFECHORDECOMP": "2025-05-21 00:00:00",
      "TNUMEFACTHILO": "FAC:F001-00046257 SOCAP"
    },
    {
      "TLOTENETT": "AU05F7-23 ",
      "TGUIAHILO": "9062",
      "TFECHGUIAHILO": "NaT",
      "TFECHORDECOMP": "NaT"
    },
    {
      "TLOTENETT": "AU05F7-31 ",
      "TGUIAHILO": "10162",
      "TFECHGUIAHILO": "NaT",
      "TFECHORDECOMP": "NaT"
    },
    {
      "TLOTENETT": "AU05F7-36",
      "TGUIAHILO": "001-10364",
      "TFECHGUIAHILO": "2025-09-17 00:00:00",
      "TPESOGUIAHILO": 2125.55,
      "TZONAORIGHILO": "Lima (Perú)",
      "TNUMEORDECOMP": 2025005487.0,
      "TFECHORDECOMP": "2025-05-21 00:00:00",
      "TNUMEFACTHILO": "FAC:F001-00047409 SOCAP"
    },
    {
      "TLOTENETT": "AU05F7-43",
      "TGUIAHILO": "001-10935",
      "TFECHGUIAHILO": "2025-11-01 00:00:00",
      "TPESOGUIAHILO": 1837.672,
      "TZONAORIGHILO": "Lima (Perú)",
      "TNUMEORDECOMP": 2025009776.0,
      "TFECHORDECOMP": "2025-09-03 00:00:00",
      "TNUMEFACTHILO": "FAC:F001-00047981 SOCAP"
    },
    {
      "TFECHGUIAHILO": "NaT",
      "TFECHORDECOMP": "NaT"
    }
  ],
  "tztotrazwebtintqyc": [
    {
      "TTICKBARR": "092525709469",
      "TNUMEOB": 4366898,
      "TTIPOPROD": "Q",
      "TCODIPROD": "S6583",
      "TDESCPROD": "ANTIMUSSOL UDF.BR LIQ.",
      "TNOMBPROV": "ARCHROMA PERÚ S.A.",
      "TORIGPROD": "BRASIL"
    },
    {
      "TTICKBARR": "092525709469",
      "TNUMEOB": 4366898,
      "TTIPOPROD": "Q",
      "TCODIPROD": "S6414",
      "TDESCPROD": "COTOBLANC PCA",
      "TNOMBPROV": "CHT PERUANA S.A.",
      "TORIGPROD": "PERÚ"
    },
    {
      "TTICKBARR": "092525709469",
      "TNUMEOB": 4366898,
      "TTIPOPROD": "Q",
      "TCODIPROD": "S6540",
      "TDESCPROD": "SODA CAUSTICA PERLAS(LABOR)",
      "TNOMBPROV": "COMINSA SAC",
      "TORIGPROD": "TAIWAN"
    },
    {
      "TTICKBARR": "092525709469",
      "TNUMEOB": 4366898,
      "TTIPOPROD": "Q",
      "TCODIPROD": "S6465",
      "TDESCPROD": "SARABID LDR",
      "TNOMBPROV": "CHT PERUANA S.A.",
      "TORIGPROD": "PERÚ"
    },
    {
      "TTICKBARR": "092525709469",
      "TNUMEOB": 4366898,
      "TTIPOPROD": "Q",
      "TCODIPROD": "S6074",
      "TDESCPROD": "SAL MOLIDA EXTRA (NACL)/CLORUR",
      "TNOMBPROV": "QUIMPAC",
      "TORIGPROD": "PERÚ"
    },
    {
      "TTICKBARR": "092525709469",
      "TNUMEOB": 4366898,
      "TTIPOPROD": "Q",
      "TCODIPROD": "S1002",
      "TDESCPROD": "ACIDO ACETICO GLACIAL",
      "TNOMBPROV": "COMINSA SAC",
      "TORIGPROD": "CHINA"
    },
    {
      "TTICKBARR": "092525709469",
      "TNUMEOB": 4366898,
      "TTIPOPROD": "Q",
      "TCODIPROD": "S6442",
      "TDESCPROD": "NEUTRACID NCS",
      "TNOMBPROV": "CHT PERUANA S.A.",
      "TORIGPROD": "PERÚ"
    }
  ],
  "quimicos_certificados": [
    {
      "nombre": "ANTIMUSSOL UDF.BR LIQ.",
      "proveedor": "ARCHROMA PERÚ S.A.",
      "origen": "BRASIL",
      "certificado": true
    },
    {
      "nombre": "COTOBLANC PCA",
      "proveedor": "CHT PERUANA S.A.",
      "origen": "PERÚ",
      "certificado": true
    },
    {
      "nombre": "SODA CAUSTICA PERLAS(LABOR)",
      "proveedor": "COMINSA SAC",
      "origen": "TAIWAN",
      "certificado": true
    },
    {
      "nombre": "SAL MOLIDA EXTRA (NACL)/CLORUR",
      "proveedor": "QUIMPAC",
      "origen": "PERÚ",
      "certificado": true
    },
    {
      "nombre": "ACIDO ACETICO GLACIAL",
      "proveedor": "COMINSA SAC",
      "origen": "CHINA",
      "certificado": true
    },
    {
      "nombre": "NEUTRACID NCS",
      "proveedor": "CHT PERUANA S.A.",
      "origen": "PERÚ",
      "certificado": true
    }
  ]
}